Workbook

Sheet Contents
A1: Volatility, Value and Risk: A Data-Driven Analysis of Bitcoin's Price Behaviour (2014-2026)
A2: and Its Implications for Financial Institutions and Businesses - Excel data analysis workbook
A4: Dataset
A5: Source | B5: Federal Reserve Bank of St. Louis, FRED (Federal Reserve Economic Data)
A6: Series | B6: CBBTCUSD - Coinbase Bitcoin price in US dollars, daily, not seasonally adjusted
A7: Coverage | B7: 01-Dec-2014 to 26-Oct-2026 (4,348 calendar days; 4,313 reported prices; 35 missing)
A8: URL | B8: https://fred.stlouisfed.org/series/CBBTCUSD
A9: Harvard reference | B9: Federal Reserve Bank of St. Louis (2026) Coinbase Bitcoin [CBBTCUSD]. Available at: https://fred.stlouisfed.org/series/CBBTCUSD (Accessed: 27 October 2026).
A11: Research objectives and statistical tools
A12: Objective | B12: Research objective | C12: Statistical tools (Excel functions) | D12: Outputs
A13: RO1 Value | B13: To examine Bitcoin's long-run price trajectory, annual returns and compound growth to evaluate its value proposition for institutions and businesses. | C13: Descriptive statistics (SUM, AVERAGE, MIN, MAX, MEDIAN, COUNTIF, AVERAGEIFS, MINIFS, MAXIFS); annual returns; CAGR; log-linear trend regression (SLOPE, RSQ); 200-day moving average | D13: Tables 1-2; Figures 1-3
A14: RO2 Volatility | B14: To measure the scale and distribution of Bitcoin's return volatility and test whether volatility has declined as the market has matured. | C14: Log returns; STDEV.S; annualised volatility (x SQRT(365)); SKEW; KURT; Jarque-Bera normality test (CHISQ.DIST.RT); frequency distribution vs NORM.DIST; 30-day rolling volatility; F-test (F.DIST.RT); SLOPE/CORREL | D14: Tables 3-6; Figures 4-6
A15: RO3 Risk | B15: To quantify Bitcoin's downside risk using measures applied by financial institutions and assess implications for treasury, payments and capital planning. | C15: Historical and parametric Value at Risk (PERCENTILE.INC, NORM.S.INV); Expected Shortfall (AVERAGEIF); VaR backtesting; square-root-of-time scaling; horizon loss probabilities (COUNTIF); maximum drawdown | D15: Tables 7-11; Figures 7-10
A17: Worksheet guide
A18: Worksheet | B18: Contents
A19: Raw_Data | B19: Unedited FRED download (with blanks) and completeness check (Table A1)
A20: Clean_Data | B20: Cleaned daily prices with formula-derived returns, moving average, drawdown, rolling volatility, horizon returns
A21: Obj1_Value | B21: Objective 1: growth summary, annual statistics, Figures 1-3
A22: Obj2_Volatility | B22: Objective 2: return distribution, annual volatility, regime test, histogram, Figures 4-6
A23: Obj3_Risk | B23: Objective 3: VaR, Expected Shortfall, horizon loss probabilities, drawdowns, Figures 7-10
A24: Summary | B24: Key empirical findings for the report conclusion (Table 12)
A25: Checks | B25: Formula integrity checks (independent calculation routes reconciled)
A27: Method notes and assumptions
A28: 1. Missing prices (35 days, mostly Dec 2014 - Jan 2015) are removed rather than interpolated, so no values are invented.
A29: 2. Return statistics start on 20-Jan-2015, when the series becomes continuous; returns spanning gaps of more than one day are excluded.
A30: 3. Log returns are used for volatility (time-additive); simple returns are used for VaR/ES (direct loss interpretation).
A31: 4. Bitcoin trades 24 hours a day, 7 days a week, so annualisation uses 365 days rather than 252 trading days.
A32: 5. The 14-Jan-2015 price of US$120 reflects thin early trading; it is retained in price levels but falls outside the return sample.
A33: 6. 2014 (December only) and 2026 (to 26 October) are partial years and are labelled as such.
A34: 7. All results are calculated with live Excel formulas; changing a blue input cell updates every dependent table and figure.
A36: Formatting legend
A37: Blue text | B37: Hard-coded input or assumption (may be changed)
A38: Black text | B38: Formula calculated on the same worksheet
A39: Green text | B39: Formula linking to another worksheet
A41: Methodological references (Harvard)
A42: Artzner, P., Delbaen, F., Eber, J.-M. and Heath, D. (1999) 'Coherent measures of risk', Mathematical Finance, 9(3), pp. 203-228.
A43: Basel Committee on Banking Supervision (2022) Prudential treatment of cryptoasset exposures. Basel: Bank for International Settlements.
A44: Cont, R. (2001) 'Empirical properties of asset returns: stylized facts and statistical issues', Quantitative Finance, 1(2), pp. 223-236.
A45: Hull, J.C. (2023) Risk Management and Financial Institutions. 6th edn. Hoboken, NJ: Wiley.
A46: Jarque, C.M. and Bera, A.K. (1980) 'Efficient tests for normality, homoscedasticity and serial independence of regression residuals', Economics Letters, 6(3), pp. 255-259.
A47: Jorion, P. (2007) Value at Risk: The New Benchmark for Managing Financial Risk. 3rd edn. New York: McGraw-Hill.

Sheet Raw_Data
A1: observation_date | B1: CBBTCUSD (US$) | D1: Table A1: Raw data completeness (FRED series CBBTCUSD)
A2: 41974 | B2: 370 | D2: Measure | E2: Value
A3: 41975 | B3: 378 | D3: Calendar days in download | E3: =COUNTA(A2:A4349) -> 4348
A4: 41976 | B4: 378 | D4: Days with a reported price | E4: =COUNT(B2:B4349) -> 4313
A5: 41977 | B5: 377.1 | D5: Days with missing price (blank) | E5: =COUNTBLANK(B2:B4349) -> 35
A6: 41978 | D6: Missing values (% of days) | E6: =E5/E3 -> 0.008049678
A7: 41979 | B7: 378 | D7: First date | E7: =MIN(A2:A4349) -> 41974
A8: 41980 | D8: Last date | E8: =MAX(A2:A4349) -> 46321
A9: 41981 | B9: 375
A10: 41982 | D10: Source: Federal Reserve Bank of St. Louis (2026) FRED series CBBTCUSD, downloaded unedited.
A11: 41983 | B11: 360.5 | D11: Missing values are concentrated in Dec 2014 - Jan 2015, before Coinbase's exchange launch (Jan 2015).
A12: 41984
A13: 41985 | B13: 350
A14: 41986
A15: 41987
A16: 41988
A17: 41989
A18: 41990
A19: 41991 | B19: 340
A20: 41992
A21: 41993
A22: 41994
A23: 41995
A24: 41996
A25: 41997
A26: 41998
A27: 41999
A28: 42000
A29: 42001
A30: 42002
A31: 42003
... A39: 42011
A40: 42012 | B40: 288.99
A41: 42013
A42: 42014
A43: 42015
A44: 42016
A45: 42017 | B45: 260
A46: 42018 | B46: 120
A47: 42019 | B47: 204.22
A48: 42020 | B48: 199.46
A49: 42021 | B49: 184
A50: 42022
A51: 42023 | B51: 225.51
A52: 42024 | B52: 218
A53: 42025 | B53: 225.51
A54: 42026 | B54: 226.32
A55: 42027 | B55: 235
A56: 42028 | B56: 240
A57: 42029 | B57: 254.53
A58: 42030 | B58: 274.48
A59: 42031 | B59: 263.65
A60: 42032 | B60: 236.09
A61: 42033 | B61: 235.03
A62: 42034 | B62: 229.07
... A2105: 44077 | B2105: 10225.82
A2106: 44078
A2107: 44079 | B2107: 10152.97
A2108: 44080 | B2108: 10255.2
A2109: 44081 | B2109: 10389.85
A2110: 44082 | B2110: 10123.21
A2111: 44083 | B2111: 10235
A2112: 44084 | B2112: 10345.95
A2113: 44085 | B2113: 10399.99
A2114: 44086 | B2114: 10444.01
A2115: 44087 | B2115: 10336.28
A2116: 44088 | B2116: 10679.33
A2117: 44089 | B2117: 10789.8
A2118: 44090 | B2118: 10953.38
... A4349: 46321 | B4349: 80056.43

Sheet Clean_Data
A1: Date | B1: Year | C1: Price (US$) | D1: Days since previous obs. | E1: Ln(price) | F1: Log return between obs. | G1: Daily log return (analysis sample) | H1: Squared daily log return | I1: Daily simple return (analysis sample) | J1: 200-day moving average (US$) | K1: Running peak (US$) | L1: Drawdown from running peak | M1: 30-day rolling volatility (annualised) | N1: 7-day return | O1: 30-day return | Q1: Analysis parameters (inputs)
A2: 41974 | B2: =YEAR(A2) -> 2014 | C2: 370 | E2: =LN(C2) -> 5.913503 | K2: =C2 -> 370 | L2: =C2/K2-1 -> 0 | N2: =IF(A2-7<$R$2,"",C2/INDEX(Clean_Data!$C$2:$C$4314,MATCH(A2-7,Clean_Data!$A$2:$A$4314,1))-1) | O2: =IF(A2-30<$R$2,"",C2/INDEX(Clean_Data!$C$2:$C$4314,MATCH(A2-30,Clean_Data!$A$2:$A$4314,1))-1) | Q2: Return-statistics start date | R2: 42024
A3: 41975 | B3: =YEAR(A3) -> 2014 | C3: 378 | D3: =A3-A2 -> 1 | E3: =LN(C3) -> 5.9348942 | F3: =LN(C3/C2) -> 0.02139119 | G3: =IF(AND(D3=1,A3>=$R$2),F3,"") | H3: =IF(G3="","",G3^2) | I3: =IF(G3="","",C3/C2-1) | K3: =MAX(K2,C3) -> 378 | L3: =C3/K3-1 -> 0 | N3: =IF(A3-7<$R$2,"",C3/INDEX(Clean_Data!$C$2:$C$4314,MATCH(A3-7,Clean_Data!$A$2:$A$4314,1))-1) | O3: =IF(A3-30<$R$2,"",C3/INDEX(Clean_Data!$C$2:$C$4314,MATCH(A3-30,Clean_Data!$A$2:$A$4314,1))-1) | Q3: Annualisation factor (days per year) | R3: 365
A4: 41976 | B4: =YEAR(A4) -> 2014 | C4: 378 | D4: =A4-A3 -> 1 | E4: =LN(C4) -> 5.9348942 | F4: =LN(C4/C3) -> 0 | G4: =IF(AND(D4=1,A4>=$R$2),F4,"") | H4: =IF(G4="","",G4^2) | I4: =IF(G4="","",C4/C3-1) | K4: =MAX(K3,C4) -> 378 | L4: =C4/K4-1 -> 0 | N4: =IF(A4-7<$R$2,"",C4/INDEX(Clean_Data!$C$2:$C$4314,MATCH(A4-7,Clean_Data!$A$2:$A$4314,1))-1) | O4: =IF(A4-30<$R$2,"",C4/INDEX(Clean_Data!$C$2:$C$4314,MATCH(A4-30,Clean_Data!$A$2:$A$4314,1))-1)
A5: 41977 | B5: =YEAR(A5) -> 2014 | C5: 377.1 | D5: =A5-A4 -> 1 | E5: =LN(C5) -> 5.9325104 | F5: =LN(C5/C4) -> -0.0023837914 | G5: =IF(AND(D5=1,A5>=$R$2),F5,"") | H5: =IF(G5="","",G5^2) | I5: =IF(G5="","",C5/C4-1) | K5: =MAX(K4,C5) -> 378 | L5: =C5/K5-1 -> -0.0023809524 | N5: =IF(A5-7<$R$2,"",C5/INDEX(Clean_Data!$C$2:$C$4314,MATCH(A5-7,Clean_Data!$A$2:$A$4314,1))-1) | O5: =IF(A5-30<$R$2,"",C5/INDEX(Clean_Data!$C$2:$C$4314,MATCH(A5-30,Clean_Data!$A$2:$A$4314,1))-1) | Q5: Notes:
A6: 41979 | B6: =YEAR(A6) -> 2014 | C6: 378 | D6: =A6-A5 -> 2 | E6: =LN(C6) -> 5.9348942 | F6: =LN(C6/C5) -> 0.0023837914 | G6: =IF(AND(D6=1,A6>=$R$2),F6,"") | H6: =IF(G6="","",G6^2) | I6: =IF(G6="","",C6/C5-1) | K6: =MAX(K5,C6) -> 378 | L6: =C6/K6-1 -> 0 | N6: =IF(A6-7<$R$2,"",C6/INDEX(Clean_Data!$C$2:$C$4314,MATCH(A6-7,Clean_Data!$A$2:$A$4314,1))-1) | O6: =IF(A6-30<$R$2,"",C6/INDEX(Clean_Data!$C$2:$C$4314,MATCH(A6-30,Clean_Data!$A$2:$A$4314,1))-1) | Q6: 1. 35 blank days in Raw_Data removed; prices are unchanged FRED values.
A7: 41981 | B7: =YEAR(A7) -> 2014 | C7: 375 | D7: =A7-A6 -> 2 | E7: =LN(C7) -> 5.926926 | F7: =LN(C7/C6) -> -0.0079681696 | G7: =IF(AND(D7=1,A7>=$R$2),F7,"") | H7: =IF(G7="","",G7^2) | I7: =IF(G7="","",C7/C6-1) | K7: =MAX(K6,C7) -> 378 | L7: =C7/K7-1 -> -0.0079365079 | N7: =IF(A7-7<$R$2,"",C7/INDEX(Clean_Data!$C$2:$C$4314,MATCH(A7-7,Clean_Data!$A$2:$A$4314,1))-1) | O7: =IF(A7-30<$R$2,"",C7/INDEX(Clean_Data!$C$2:$C$4314,MATCH(A7-30,Clean_Data!$A$2:$A$4314,1))-1) | Q7: 2. Return statistics start 20-Jan-2015, the first day of continuous daily
A8: 41983 | B8: =YEAR(A8) -> 2014 | C8: 360.5 | D8: =A8-A7 -> 2 | E8: =LN(C8) -> 5.887492 | F8: =LN(C8/C7) -> -0.039434069 | G8: =IF(AND(D8=1,A8>=$R$2),F8,"") | H8: =IF(G8="","",G8^2) | I8: =IF(G8="","",C8/C7-1) | K8: =MAX(K7,C8) -> 378 | L8: =C8/K8-1 -> -0.046296296 | N8: =IF(A8-7<$R$2,"",C8/INDEX(Clean_Data!$C$2:$C$4314,MATCH(A8-7,Clean_Data!$A$2:$A$4314,1))-1) | O8: =IF(A8-30<$R$2,"",C8/INDEX(Clean_Data!$C$2:$C$4314,MATCH(A8-30,Clean_Data!$A$2:$A$4314,1))-1) | Q8: pricing (earlier data are sparse and include an anomalous $120 print).
A9: 41985 | B9: =YEAR(A9) -> 2014 | C9: 350 | D9: =A9-A8 -> 2 | E9: =LN(C9) -> 5.8579332 | F9: =LN(C9/C8) -> -0.029558802 | G9: =IF(AND(D9=1,A9>=$R$2),F9,"") | H9: =IF(G9="","",G9^2) | I9: =IF(G9="","",C9/C8-1) | K9: =MAX(K8,C9) -> 378 | L9: =C9/K9-1 -> -0.074074074 | N9: =IF(A9-7<$R$2,"",C9/INDEX(Clean_Data!$C$2:$C$4314,MATCH(A9-7,Clean_Data!$A$2:$A$4314,1))-1) | O9: =IF(A9-30<$R$2,"",C9/INDEX(Clean_Data!$C$2:$C$4314,MATCH(A9-30,Clean_Data!$A$2:$A$4314,1))-1) | Q9: 3. Returns spanning more than one calendar day are excluded (col. G, I).
A10: 41991 | B10: =YEAR(A10) -> 2014 | C10: 340 | D10: =A10-A9 -> 6 | E10: =LN(C10) -> 5.8289456 | F10: =LN(C10/C9) -> -0.028987537 | G10: =IF(AND(D10=1,A10>=$R$2),F10,"") | H10: =IF(G10="","",G10^2) | I10: =IF(G10="","",C10/C9-1) | K10: =MAX(K9,C10) -> 378 | L10: =C10/K10-1 -> -0.1005291 | N10: =IF(A10-7<$R$2,"",C10/INDEX(Clean_Data!$C$2:$C$4314,MATCH(A10-7,Clean_Data!$A$2:$A$4314,1))-1) | O10: =IF(A10-30<$R$2,"",C10/INDEX(Clean_Data!$C$2:$C$4314,MATCH(A10-30,Clean_Data!$A$2:$A$4314,1))-1) | Q10: 4. Bitcoin trades 24/7, so volatility is annualised with sqrt(365).
A11: 42012 | B11: =YEAR(A11) -> 2015 | C11: 288.99 | D11: =A11-A10 -> 21 | E11: =LN(C11) -> 5.6663921 | F11: =LN(C11/C10) -> -0.16255353 | G11: =IF(AND(D11=1,A11>=$R$2),F11,"") | H11: =IF(G11="","",G11^2) | I11: =IF(G11="","",C11/C10-1) | K11: =MAX(K10,C11) -> 378 | L11: =C11/K11-1 -> -0.23547619 | N11: =IF(A11-7<$R$2,"",C11/INDEX(Clean_Data!$C$2:$C$4314,MATCH(A11-7,Clean_Data!$A$2:$A$4314,1))-1) | O11: =IF(A11-30<$R$2,"",C11/INDEX(Clean_Data!$C$2:$C$4314,MATCH(A11-30,Clean_Data!$A$2:$A$4314,1))-1) | Q11: 5. 7- and 30-day returns are overlapping windows (calendar-day lookback).
A12: 42017 | B12: =YEAR(A12) -> 2015 | C12: 260 | D12: =A12-A11 -> 5 | E12: =LN(C12) -> 5.5606816 | F12: =LN(C12/C11) -> -0.10571045 | G12: =IF(AND(D12=1,A12>=$R$2),F12,"") | H12: =IF(G12="","",G12^2) | I12: =IF(G12="","",C12/C11-1) | K12: =MAX(K11,C12) -> 378 | L12: =C12/K12-1 -> -0.31216931 | N12: =IF(A12-7<$R$2,"",C12/INDEX(Clean_Data!$C$2:$C$4314,MATCH(A12-7,Clean_Data!$A$2:$A$4314,1))-1) | O12: =IF(A12-30<$R$2,"",C12/INDEX(Clean_Data!$C$2:$C$4314,MATCH(A12-30,Clean_Data!$A$2:$A$4314,1))-1)
A13: 42018 | B13: =YEAR(A13) -> 2015 | C13: 120 | D13: =A13-A12 -> 1 | E13: =LN(C13) -> 4.7874917 | F13: =LN(C13/C12) -> -0.77318989 | G13: =IF(AND(D13=1,A13>=$R$2),F13,"") | H13: =IF(G13="","",G13^2) | I13: =IF(G13="","",C13/C12-1) | K13: =MAX(K12,C13) -> 378 | L13: =C13/K13-1 -> -0.68253968 | N13: =IF(A13-7<$R$2,"",C13/INDEX(Clean_Data!$C$2:$C$4314,MATCH(A13-7,Clean_Data!$A$2:$A$4314,1))-1) | O13: =IF(A13-30<$R$2,"",C13/INDEX(Clean_Data!$C$2:$C$4314,MATCH(A13-30,Clean_Data!$A$2:$A$4314,1))-1)
A14: 42019 | B14: =YEAR(A14) -> 2015 | C14: 204.22 | D14: =A14-A13 -> 1 | E14: =LN(C14) -> 5.3191978 | F14: =LN(C14/C13) -> 0.5317061 | G14: =IF(AND(D14=1,A14>=$R$2),F14,"") | H14: =IF(G14="","",G14^2) | I14: =IF(G14="","",C14/C13-1) | K14: =MAX(K13,C14) -> 378 | L14: =C14/K14-1 -> -0.45973545 | N14: =IF(A14-7<$R$2,"",C14/INDEX(Clean_Data!$C$2:$C$4314,MATCH(A14-7,Clean_Data!$A$2:$A$4314,1))-1) | O14: =IF(A14-30<$R$2,"",C14/INDEX(Clean_Data!$C$2:$C$4314,MATCH(A14-30,Clean_Data!$A$2:$A$4314,1))-1)
A15: 42020 | B15: =YEAR(A15) -> 2015 | C15: 199.46 | D15: =A15-A14 -> 1 | E15: =LN(C15) -> 5.2956137 | F15: =LN(C15/C14) -> -0.023584129 | G15: =IF(AND(D15=1,A15>=$R$2),F15,"") | H15: =IF(G15="","",G15^2) | I15: =IF(G15="","",C15/C14-1) | K15: =MAX(K14,C15) -> 378 | L15: =C15/K15-1 -> -0.47232804 | N15: =IF(A15-7<$R$2,"",C15/INDEX(Clean_Data!$C$2:$C$4314,MATCH(A15-7,Clean_Data!$A$2:$A$4314,1))-1) | O15: =IF(A15-30<$R$2,"",C15/INDEX(Clean_Data!$C$2:$C$4314,MATCH(A15-30,Clean_Data!$A$2:$A$4314,1))-1)
A16: 42021 | B16: =YEAR(A16) -> 2015 | C16: 184 | D16: =A16-A15 -> 1 | E16: =LN(C16) -> 5.2149358 | F16: =LN(C16/C15) -> -0.080677957 | G16: =IF(AND(D16=1,A16>=$R$2),F16,"") | H16: =IF(G16="","",G16^2) | I16: =IF(G16="","",C16/C15-1) | K16: =MAX(K15,C16) -> 378 | L16: =C16/K16-1 -> -0.51322751 | N16: =IF(A16-7<$R$2,"",C16/INDEX(Clean_Data!$C$2:$C$4314,MATCH(A16-7,Clean_Data!$A$2:$A$4314,1))-1) | O16: =IF(A16-30<$R$2,"",C16/INDEX(Clean_Data!$C$2:$C$4314,MATCH(A16-30,Clean_Data!$A$2:$A$4314,1))-1)
A17: 42023 | B17: =YEAR(A17) -> 2015 | C17: 225.51 | D17: =A17-A16 -> 2 | E17: =LN(C17) -> 5.4183645 | F17: =LN(C17/C16) -> 0.20342875 | G17: =IF(AND(D17=1,A17>=$R$2),F17,"") | H17: =IF(G17="","",G17^2) | I17: =IF(G17="","",C17/C16-1) | K17: =MAX(K16,C17) -> 378 | L17: =C17/K17-1 -> -0.4034127 | N17: =IF(A17-7<$R$2,"",C17/INDEX(Clean_Data!$C$2:$C$4314,MATCH(A17-7,Clean_Data!$A$2:$A$4314,1))-1) | O17: =IF(A17-30<$R$2,"",C17/INDEX(Clean_Data!$C$2:$C$4314,MATCH(A17-30,Clean_Data!$A$2:$A$4314,1))-1)
A18: 42024 | B18: =YEAR(A18) -> 2015 | C18: 218 | D18: =A18-A17 -> 1 | E18: =LN(C18) -> 5.3844951 | F18: =LN(C18/C17) -> -0.033869441 | G18: =IF(AND(D18=1,A18>=$R$2),F18,"") -> -0.033869441 | H18: =IF(G18="","",G18^2) -> 0.001147139 | I18: =IF(G18="","",C18/C17-1) -> -0.033302293 | K18: =MAX(K17,C18) -> 378 | L18: =C18/K18-1 -> -0.42328042 | N18: =IF(A18-7<$R$2,"",C18/INDEX(Clean_Data!$C$2:$C$4314,MATCH(A18-7,Clean_Data!$A$2:$A$4314,1))-1) | O18: =IF(A18-30<$R$2,"",C18/INDEX(Clean_Data!$C$2:$C$4314,MATCH(A18-30,Clean_Data!$A$2:$A$4314,1))-1)
A19: 42025 | B19: =YEAR(A19) -> 2015 | C19: 225.51 | D19: =A19-A18 -> 1 | E19: =LN(C19) -> 5.4183645 | F19: =LN(C19/C18) -> 0.033869441 | G19: =IF(AND(D19=1,A19>=$R$2),F19,"") -> 0.033869441 | H19: =IF(G19="","",G19^2) -> 0.001147139 | I19: =IF(G19="","",C19/C18-1) -> 0.034449541 | K19: =MAX(K18,C19) -> 378 | L19: =C19/K19-1 -> -0.4034127 | N19: =IF(A19-7<$R$2,"",C19/INDEX(Clean_Data!$C$2:$C$4314,MATCH(A19-7,Clean_Data!$A$2:$A$4314,1))-1) | O19: =IF(A19-30<$R$2,"",C19/INDEX(Clean_Data!$C$2:$C$4314,MATCH(A19-30,Clean_Data!$A$2:$A$4314,1))-1)
A20: 42026 | B20: =YEAR(A20) -> 2015 | C20: 226.32 | D20: =A20-A19 -> 1 | E20: =LN(C20) -> 5.4219499 | F20: =LN(C20/C19) -> 0.0035854231 | G20: =IF(AND(D20=1,A20>=$R$2),F20,"") -> 0.0035854231 | H20: =IF(G20="","",G20^2) -> 1.2855259e-05 | I20: =IF(G20="","",C20/C19-1) -> 0.0035918585 | K20: =MAX(K19,C20) -> 378 | L20: =C20/K20-1 -> -0.40126984 | N20: =IF(A20-7<$R$2,"",C20/INDEX(Clean_Data!$C$2:$C$4314,MATCH(A20-7,Clean_Data!$A$2:$A$4314,1))-1) | O20: =IF(A20-30<$R$2,"",C20/INDEX(Clean_Data!$C$2:$C$4314,MATCH(A20-30,Clean_Data!$A$2:$A$4314,1))-1)
A21: 42027 | B21: =YEAR(A21) -> 2015 | C21: 235 | D21: =A21-A20 -> 1 | E21: =LN(C21) -> 5.4595855 | F21: =LN(C21/C20) -> 0.037635587 | G21: =IF(AND(D21=1,A21>=$R$2),F21,"") -> 0.037635587 | H21: =IF(G21="","",G21^2) -> 0.0014164374 | I21: =IF(G21="","",C21/C20-1) -> 0.038352775 | K21: =MAX(K20,C21) -> 378 | L21: =C21/K21-1 -> -0.37830688 | N21: =IF(A21-7<$R$2,"",C21/INDEX(Clean_Data!$C$2:$C$4314,MATCH(A21-7,Clean_Data!$A$2:$A$4314,1))-1) | O21: =IF(A21-30<$R$2,"",C21/INDEX(Clean_Data!$C$2:$C$4314,MATCH(A21-30,Clean_Data!$A$2:$A$4314,1))-1)
A22: 42028 | B22: =YEAR(A22) -> 2015 | C22: 240 | D22: =A22-A21 -> 1 | E22: =LN(C22) -> 5.4806389 | F22: =LN(C22/C21) -> 0.021053409 | G22: =IF(AND(D22=1,A22>=$R$2),F22,"") -> 0.021053409 | H22: =IF(G22="","",G22^2) -> 0.00044324604 | I22: =IF(G22="","",C22/C21-1) -> 0.021276596 | K22: =MAX(K21,C22) -> 378 | L22: =C22/K22-1 -> -0.36507937 | N22: =IF(A22-7<$R$2,"",C22/INDEX(Clean_Data!$C$2:$C$4314,MATCH(A22-7,Clean_Data!$A$2:$A$4314,1))-1) | O22: =IF(A22-30<$R$2,"",C22/INDEX(Clean_Data!$C$2:$C$4314,MATCH(A22-30,Clean_Data!$A$2:$A$4314,1))-1)
A23: 42029 | B23: =YEAR(A23) -> 2015 | C23: 254.53 | D23: =A23-A22 -> 1 | E23: =LN(C23) -> 5.5394187 | F23: =LN(C23/C22) -> 0.058779784 | G23: =IF(AND(D23=1,A23>=$R$2),F23,"") -> 0.058779784 | H23: =IF(G23="","",G23^2) -> 0.003455063 | I23: =IF(G23="","",C23/C22-1) -> 0.060541667 | K23: =MAX(K22,C23) -> 378 | L23: =C23/K23-1 -> -0.32664021 | N23: =IF(A23-7<$R$2,"",C23/INDEX(Clean_Data!$C$2:$C$4314,MATCH(A23-7,Clean_Data!$A$2:$A$4314,1))-1) | O23: =IF(A23-30<$R$2,"",C23/INDEX(Clean_Data!$C$2:$C$4314,MATCH(A23-30,Clean_Data!$A$2:$A$4314,1))-1)
... A30: 42036 | B30: =YEAR(A30) -> 2015 | C30: 228.99 | D30: =A30-A29 -> 1 | E30: =LN(C30) -> 5.4336783 | F30: =LN(C30/C29) -> 0.047121179 | G30: =IF(AND(D30=1,A30>=$R$2),F30,"") -> 0.047121179 | H30: =IF(G30="","",G30^2) -> 0.0022204055 | I30: =IF(G30="","",C30/C29-1) -> 0.048249027 | K30: =MAX(K29,C30) -> 378 | L30: =C30/K30-1 -> -0.39420635 | N30: =IF(A30-7<$R$2,"",C30/INDEX(Clean_Data!$C$2:$C$4314,MATCH(A30-7,Clean_Data!$A$2:$A$4314,1))-1) -> -0.10034181 | O30: =IF(A30-30<$R$2,"",C30/INDEX(Clean_Data!$C$2:$C$4314,MATCH(A30-30,Clean_Data!$A$2:$A$4314,1))-1)
A31: 42037 | B31: =YEAR(A31) -> 2015 | C31: 237.83 | D31: =A31-A30 -> 1 | E31: =LN(C31) -> 5.4715561 | F31: =LN(C31/C30) -> 0.037877798 | G31: =IF(AND(D31=1,A31>=$R$2),F31,"") -> 0.037877798 | H31: =IF(G31="","",G31^2) -> 0.0014347276 | I31: =IF(G31="","",C31/C30-1) -> 0.038604306 | K31: =MAX(K30,C31) -> 378 | L31: =C31/K31-1 -> -0.37082011 | M31: =IF(COUNT(G2:G31)<20,"",_xlfn.STDEV.S(G2:G31)*SQRT($R$3)) | N31: =IF(A31-7<$R$2,"",C31/INDEX(Clean_Data!$C$2:$C$4314,MATCH(A31-7,Clean_Data!$A$2:$A$4314,1))-1) -> -0.13352521 | O31: =IF(A31-30<$R$2,"",C31/INDEX(Clean_Data!$C$2:$C$4314,MATCH(A31-30,Clean_Data!$A$2:$A$4314,1))-1)
A32: 42038 | B32: =YEAR(A32) -> 2015 | C32: 228.58 | D32: =A32-A31 -> 1 | E32: =LN(C32) -> 5.4318863 | F32: =LN(C32/C31) -> -0.039669874 | G32: =IF(AND(D32=1,A32>=$R$2),F32,"") -> -0.039669874 | H32: =IF(G32="","",G32^2) -> 0.0015736989 | I32: =IF(G32="","",C32/C31-1) -> -0.038893327 | K32: =MAX(K31,C32) -> 378 | L32: =C32/K32-1 -> -0.39529101 | M32: =IF(COUNT(G3:G32)<20,"",_xlfn.STDEV.S(G3:G32)*SQRT($R$3)) | N32: =IF(A32-7<$R$2,"",C32/INDEX(Clean_Data!$C$2:$C$4314,MATCH(A32-7,Clean_Data!$A$2:$A$4314,1))-1) -> -0.13301726 | O32: =IF(A32-30<$R$2,"",C32/INDEX(Clean_Data!$C$2:$C$4314,MATCH(A32-30,Clean_Data!$A$2:$A$4314,1))-1)
A33: 42039 | B33: =YEAR(A33) -> 2015 | C33: 227.11 | D33: =A33-A32 -> 1 | E33: =LN(C33) -> 5.4254345 | F33: =LN(C33/C32) -> -0.0064517769 | G33: =IF(AND(D33=1,A33>=$R$2),F33,"") -> -0.0064517769 | H33: =IF(G33="","",G33^2) -> 4.1625425e-05 | I33: =IF(G33="","",C33/C32-1) -> -0.0064310088 | K33: =MAX(K32,C33) -> 378 | L33: =C33/K33-1 -> -0.39917989 | M33: =IF(COUNT(G4:G33)<20,"",_xlfn.STDEV.S(G4:G33)*SQRT($R$3)) | N33: =IF(A33-7<$R$2,"",C33/INDEX(Clean_Data!$C$2:$C$4314,MATCH(A33-7,Clean_Data!$A$2:$A$4314,1))-1) -> -0.038036342 | O33: =IF(A33-30<$R$2,"",C33/INDEX(Clean_Data!$C$2:$C$4314,MATCH(A33-30,Clean_Data!$A$2:$A$4314,1))-1)
A34: 42040 | B34: =YEAR(A34) -> 2015 | C34: 216.76 | D34: =A34-A33 -> 1 | E34: =LN(C34) -> 5.3787908 | F34: =LN(C34/C33) -> -0.046643731 | G34: =IF(AND(D34=1,A34>=$R$2),F34,"") -> -0.046643731 | H34: =IF(G34="","",G34^2) -> 0.0021756376 | I34: =IF(G34="","",C34/C33-1) -> -0.04557263 | K34: =MAX(K33,C34) -> 378 | L34: =C34/K34-1 -> -0.42656085 | M34: =IF(COUNT(G5:G34)<20,"",_xlfn.STDEV.S(G5:G34)*SQRT($R$3)) | N34: =IF(A34-7<$R$2,"",C34/INDEX(Clean_Data!$C$2:$C$4314,MATCH(A34-7,Clean_Data!$A$2:$A$4314,1))-1) -> -0.077734757 | O34: =IF(A34-30<$R$2,"",C34/INDEX(Clean_Data!$C$2:$C$4314,MATCH(A34-30,Clean_Data!$A$2:$A$4314,1))-1)
A35: 42041 | B35: =YEAR(A35) -> 2015 | C35: 223.2 | D35: =A35-A34 -> 1 | E35: =LN(C35) -> 5.4080682 | F35: =LN(C35/C34) -> 0.02927748 | G35: =IF(AND(D35=1,A35>=$R$2),F35,"") -> 0.02927748 | H35: =IF(G35="","",G35^2) -> 0.00085717082 | I35: =IF(G35="","",C35/C34-1) -> 0.029710279 | K35: =MAX(K34,C35) -> 378 | L35: =C35/K35-1 -> -0.40952381 | M35: =IF(COUNT(G6:G35)<20,"",_xlfn.STDEV.S(G6:G35)*SQRT($R$3)) | N35: =IF(A35-7<$R$2,"",C35/INDEX(Clean_Data!$C$2:$C$4314,MATCH(A35-7,Clean_Data!$A$2:$A$4314,1))-1) -> -0.025625355 | O35: =IF(A35-30<$R$2,"",C35/INDEX(Clean_Data!$C$2:$C$4314,MATCH(A35-30,Clean_Data!$A$2:$A$4314,1))-1)
A36: 42042 | B36: =YEAR(A36) -> 2015 | C36: 229 | D36: =A36-A35 -> 1 | E36: =LN(C36) -> 5.433722 | F36: =LN(C36/C35) -> 0.025653773 | G36: =IF(AND(D36=1,A36>=$R$2),F36,"") -> 0.025653773 | H36: =IF(G36="","",G36^2) -> 0.00065811607 | I36: =IF(G36="","",C36/C35-1) -> 0.025985663 | K36: =MAX(K35,C36) -> 378 | L36: =C36/K36-1 -> -0.39417989 | M36: =IF(COUNT(G7:G36)<20,"",_xlfn.STDEV.S(G7:G36)*SQRT($R$3)) | N36: =IF(A36-7<$R$2,"",C36/INDEX(Clean_Data!$C$2:$C$4314,MATCH(A36-7,Clean_Data!$A$2:$A$4314,1))-1) -> 0.048294804 | O36: =IF(A36-30<$R$2,"",C36/INDEX(Clean_Data!$C$2:$C$4314,MATCH(A36-30,Clean_Data!$A$2:$A$4314,1))-1)
A37: 42043 | B37: =YEAR(A37) -> 2015 | C37: 223.99 | D37: =A37-A36 -> 1 | E37: =LN(C37) -> 5.4116014 | F37: =LN(C37/C36) -> -0.022120596 | G37: =IF(AND(D37=1,A37>=$R$2),F37,"") -> -0.022120596 | H37: =IF(G37="","",G37^2) -> 0.00048932075 | I37: =IF(G37="","",C37/C36-1) -> -0.021877729 | K37: =MAX(K36,C37) -> 378 | L37: =C37/K37-1 -> -0.40743386 | M37: =IF(COUNT(G8:G37)<20,"",_xlfn.STDEV.S(G8:G37)*SQRT($R$3)) -> 0.87119597 | N37: =IF(A37-7<$R$2,"",C37/INDEX(Clean_Data!$C$2:$C$4314,MATCH(A37-7,Clean_Data!$A$2:$A$4314,1))-1) -> -0.021835015 | O37: =IF(A37-30<$R$2,"",C37/INDEX(Clean_Data!$C$2:$C$4314,MATCH(A37-30,Clean_Data!$A$2:$A$4314,1))-1)
A38: 42044 | B38: =YEAR(A38) -> 2015 | C38: 221.1 | D38: =A38-A37 -> 1 | E38: =LN(C38) -> 5.3986151 | F38: =LN(C38/C37) -> -0.01298632 | G38: =IF(AND(D38=1,A38>=$R$2),F38,"") -> -0.01298632 | H38: =IF(G38="","",G38^2) -> 0.00016864451 | I38: =IF(G38="","",C38/C37-1) -> -0.012902362 | K38: =MAX(K37,C38) -> 378 | L38: =C38/K38-1 -> -0.41507937 | M38: =IF(COUNT(G9:G38)<20,"",_xlfn.STDEV.S(G9:G38)*SQRT($R$3)) -> 0.85077249 | N38: =IF(A38-7<$R$2,"",C38/INDEX(Clean_Data!$C$2:$C$4314,MATCH(A38-7,Clean_Data!$A$2:$A$4314,1))-1) -> -0.070344364 | O38: =IF(A38-30<$R$2,"",C38/INDEX(Clean_Data!$C$2:$C$4314,MATCH(A38-30,Clean_Data!$A$2:$A$4314,1))-1)
A39: 42045 | B39: =YEAR(A39) -> 2015 | C39: 220.87 | D39: =A39-A38 -> 1 | E39: =LN(C39) -> 5.3975743 | F39: =LN(C39/C38) -> -0.0010407947 | G39: =IF(AND(D39=1,A39>=$R$2),F39,"") -> -0.0010407947 | H39: =IF(G39="","",G39^2) -> 1.0832536e-06 | I39: =IF(G39="","",C39/C38-1) -> -0.0010402533 | K39: =MAX(K38,C39) -> 378 | L39: =C39/K39-1 -> -0.41568783 | M39: =IF(COUNT(G10:G39)<20,"",_xlfn.STDEV.S(G10:G39)*SQRT($R$3)) -> 0.83026904 | N39: =IF(A39-7<$R$2,"",C39/INDEX(Clean_Data!$C$2:$C$4314,MATCH(A39-7,Clean_Data!$A$2:$A$4314,1))-1) -> -0.033729985 | O39: =IF(A39-30<$R$2,"",C39/INDEX(Clean_Data!$C$2:$C$4314,MATCH(A39-30,Clean_Data!$A$2:$A$4314,1))-1)
A40: 42046 | B40: =YEAR(A40) -> 2015 | C40: 219.81 | D40: =A40-A39 -> 1 | E40: =LN(C40) -> 5.3927635 | F40: =LN(C40/C39) -> -0.0048107563 | G40: =IF(AND(D40=1,A40>=$R$2),F40,"") -> -0.0048107563 | H40: =IF(G40="","",G40^2) -> 2.3143376e-05 | I40: =IF(G40="","",C40/C39-1) -> -0.0047992032 | K40: =MAX(K39,C40) -> 378 | L40: =C40/K40-1 -> -0.41849206 | M40: =IF(COUNT(G11:G40)<20,"",_xlfn.STDEV.S(G11:G40)*SQRT($R$3)) -> 0.811326 | N40: =IF(A40-7<$R$2,"",C40/INDEX(Clean_Data!$C$2:$C$4314,MATCH(A40-7,Clean_Data!$A$2:$A$4314,1))-1) -> -0.032143014 | O40: =IF(A40-30<$R$2,"",C40/INDEX(Clean_Data!$C$2:$C$4314,MATCH(A40-30,Clean_Data!$A$2:$A$4314,1))-1)
A41: 42047 | B41: =YEAR(A41) -> 2015 | C41: 223.21 | D41: =A41-A40 -> 1 | E41: =LN(C41) -> 5.408113 | F41: =LN(C41/C40) -> 0.015349496 | G41: =IF(AND(D41=1,A41>=$R$2),F41,"") -> 0.015349496 | H41: =IF(G41="","",G41^2) -> 0.00023560701 | I41: =IF(G41="","",C41/C40-1) -> 0.015467904 | K41: =MAX(K40,C41) -> 378 | L41: =C41/K41-1 -> -0.40949735 | M41: =IF(COUNT(G12:G41)<20,"",_xlfn.STDEV.S(G12:G41)*SQRT($R$3)) -> 0.79608545 | N41: =IF(A41-7<$R$2,"",C41/INDEX(Clean_Data!$C$2:$C$4314,MATCH(A41-7,Clean_Data!$A$2:$A$4314,1))-1) -> 0.029756413 | O41: =IF(A41-30<$R$2,"",C41/INDEX(Clean_Data!$C$2:$C$4314,MATCH(A41-30,Clean_Data!$A$2:$A$4314,1))-1)
A42: 42048 | B42: =YEAR(A42) -> 2015 | C42: 236.49 | D42: =A42-A41 -> 1 | E42: =LN(C42) -> 5.4659059 | F42: =LN(C42/C41) -> 0.057792891 | G42: =IF(AND(D42=1,A42>=$R$2),F42,"") -> 0.057792891 | H42: =IF(G42="","",G42^2) -> 0.0033400183 | I42: =IF(G42="","",C42/C41-1) -> 0.059495542 | K42: =MAX(K41,C42) -> 378 | L42: =C42/K42-1 -> -0.37436508 | M42: =IF(COUNT(G13:G42)<20,"",_xlfn.STDEV.S(G13:G42)*SQRT($R$3)) -> 0.81045263 | N42: =IF(A42-7<$R$2,"",C42/INDEX(Clean_Data!$C$2:$C$4314,MATCH(A42-7,Clean_Data!$A$2:$A$4314,1))-1) -> 0.059543011 | O42: =IF(A42-30<$R$2,"",C42/INDEX(Clean_Data!$C$2:$C$4314,MATCH(A42-30,Clean_Data!$A$2:$A$4314,1))-1)
... A200: 42206 | B200: =YEAR(A200) -> 2015 | C200: 277.32 | D200: =A200-A199 -> 1 | E200: =LN(C200) -> 5.6251721 | F200: =LN(C200/C199) -> -0.0096175291 | G200: =IF(AND(D200=1,A200>=$R$2),F200,"") -> -0.0096175291 | H200: =IF(G200="","",G200^2) -> 9.2496866e-05 | I200: =IF(G200="","",C200/C199-1) -> -0.0095714286 | K200: =MAX(K199,C200) -> 378 | L200: =C200/K200-1 -> -0.26634921 | M200: =IF(COUNT(G171:G200)<20,"",_xlfn.STDEV.S(G171:G200)*SQRT($R$3)) -> 0.49761265 | N200: =IF(A200-7<$R$2,"",C200/INDEX(Clean_Data!$C$2:$C$4314,MATCH(A200-7,Clean_Data!$A$2:$A$4314,1))-1) -> -0.035442245 | O200: =IF(A200-30<$R$2,"",C200/INDEX(Clean_Data!$C$2:$C$4314,MATCH(A200-30,Clean_Data!$A$2:$A$4314,1))-1) -> 0.13349138
A201: 42207 | B201: =YEAR(A201) -> 2015 | C201: 277.89 | D201: =A201-A200 -> 1 | E201: =LN(C201) -> 5.6272254 | F201: =LN(C201/C200) -> 0.0020532779 | G201: =IF(AND(D201=1,A201>=$R$2),F201,"") -> 0.0020532779 | H201: =IF(G201="","",G201^2) -> 4.21595e-06 | I201: =IF(G201="","",C201/C200-1) -> 0.0020553873 | J201: =AVERAGE(C2:C201) -> 251.42965 | K201: =MAX(K200,C201) -> 378 | L201: =C201/K201-1 -> -0.26484127 | M201: =IF(COUNT(G172:G201)<20,"",_xlfn.STDEV.S(G172:G201)*SQRT($R$3)) -> 0.49694541 | N201: =IF(A201-7<$R$2,"",C201/INDEX(Clean_Data!$C$2:$C$4314,MATCH(A201-7,Clean_Data!$A$2:$A$4314,1))-1) -> -0.027336367 | O201: =IF(A201-30<$R$2,"",C201/INDEX(Clean_Data!$C$2:$C$4314,MATCH(A201-30,Clean_Data!$A$2:$A$4314,1))-1) -> 0.12278788
A202: 42208 | B202: =YEAR(A202) -> 2015 | C202: 277.39 | D202: =A202-A201 -> 1 | E202: =LN(C202) -> 5.6254245 | F202: =LN(C202/C201) -> -0.0018008937 | G202: =IF(AND(D202=1,A202>=$R$2),F202,"") -> -0.0018008937 | H202: =IF(G202="","",G202^2) -> 3.2432182e-06 | I202: =IF(G202="","",C202/C201-1) -> -0.0017992731 | J202: =AVERAGE(C3:C202) -> 250.9666 | K202: =MAX(K201,C202) -> 378 | L202: =C202/K202-1 -> -0.26616402 | M202: =IF(COUNT(G173:G202)<20,"",_xlfn.STDEV.S(G173:G202)*SQRT($R$3)) -> 0.49406673 | N202: =IF(A202-7<$R$2,"",C202/INDEX(Clean_Data!$C$2:$C$4314,MATCH(A202-7,Clean_Data!$A$2:$A$4314,1))-1) -> -0.007122915 | O202: =IF(A202-30<$R$2,"",C202/INDEX(Clean_Data!$C$2:$C$4314,MATCH(A202-30,Clean_Data!$A$2:$A$4314,1))-1) -> 0.13442663
A203: 42209 | B203: =YEAR(A203) -> 2015 | C203: 289.12 | D203: =A203-A202 -> 1 | E203: =LN(C203) -> 5.6668418 | F203: =LN(C203/C202) -> 0.041417369 | G203: =IF(AND(D203=1,A203>=$R$2),F203,"") -> 0.041417369 | H203: =IF(G203="","",G203^2) -> 0.0017153984 | I203: =IF(G203="","",C203/C202-1) -> 0.042287033 | J203: =AVERAGE(C4:C203) -> 250.5222 | K203: =MAX(K202,C203) -> 378 | L203: =C203/K203-1 -> -0.23513228 | M203: =IF(COUNT(G174:G203)<20,"",_xlfn.STDEV.S(G174:G203)*SQRT($R$3)) -> 0.50353017 | N203: =IF(A203-7<$R$2,"",C203/INDEX(Clean_Data!$C$2:$C$4314,MATCH(A203-7,Clean_Data!$A$2:$A$4314,1))-1) -> 0.030436952 | O203: =IF(A203-30<$R$2,"",C203/INDEX(Clean_Data!$C$2:$C$4314,MATCH(A203-30,Clean_Data!$A$2:$A$4314,1))-1) -> 0.20446592
A204: 42210 | B204: =YEAR(A204) -> 2015 | C204: 289.7 | D204: =A204-A203 -> 1 | E204: =LN(C204) -> 5.6688459 | F204: =LN(C204/C203) -> 0.0020040779 | G204: =IF(AND(D204=1,A204>=$R$2),F204,"") -> 0.0020040779 | H204: =IF(G204="","",G204^2) -> 4.0163284e-06 | I204: =IF(G204="","",C204/C203-1) -> 0.0020060874 | J204: =AVERAGE(C5:C204) -> 250.0807 | K204: =MAX(K203,C204) -> 378 | L204: =C204/K204-1 -> -0.23359788 | M204: =IF(COUNT(G175:G204)<20,"",_xlfn.STDEV.S(G175:G204)*SQRT($R$3)) -> 0.50354852 | N204: =IF(A204-7<$R$2,"",C204/INDEX(Clean_Data!$C$2:$C$4314,MATCH(A204-7,Clean_Data!$A$2:$A$4314,1))-1) -> 0.043174535 | O204: =IF(A204-30<$R$2,"",C204/INDEX(Clean_Data!$C$2:$C$4314,MATCH(A204-30,Clean_Data!$A$2:$A$4314,1))-1) -> 0.19493483
A205: 42211 | B205: =YEAR(A205) -> 2015 | C205: 293.89 | D205: =A205-A204 -> 1 | E205: =LN(C205) -> 5.6832055 | F205: =LN(C205/C204) -> 0.014359643 | G205: =IF(AND(D205=1,A205>=$R$2),F205,"") -> 0.014359643 | H205: =IF(G205="","",G205^2) -> 0.00020619934 | I205: =IF(G205="","",C205/C204-1) -> 0.014463238 | J205: =AVERAGE(C6:C205) -> 249.66465 | K205: =MAX(K204,C205) -> 378 | L205: =C205/K205-1 -> -0.22251323 | M205: =IF(COUNT(G176:G205)<20,"",_xlfn.STDEV.S(G176:G205)*SQRT($R$3)) -> 0.50420968 | N205: =IF(A205-7<$R$2,"",C205/INDEX(Clean_Data!$C$2:$C$4314,MATCH(A205-7,Clean_Data!$A$2:$A$4314,1))-1) -> 0.066325605 | O205: =IF(A205-30<$R$2,"",C205/INDEX(Clean_Data!$C$2:$C$4314,MATCH(A205-30,Clean_Data!$A$2:$A$4314,1))-1) -> 0.20942387
A206: 42212 | B206: =YEAR(A206) -> 2015 | C206: 294.21 | D206: =A206-A205 -> 1 | E206: =LN(C206) -> 5.6842938 | F206: =LN(C206/C205) -> 0.0010882504 | G206: =IF(AND(D206=1,A206>=$R$2),F206,"") -> 0.0010882504 | H206: =IF(G206="","",G206^2) -> 1.1842889e-06 | I206: =IF(G206="","",C206/C205-1) -> 0.0010888428 | J206: =AVERAGE(C7:C206) -> 249.2457 | K206: =MAX(K205,C206) -> 378 | L206: =C206/K206-1 -> -0.22166667 | M206: =IF(COUNT(G177:G206)<20,"",_xlfn.STDEV.S(G177:G206)*SQRT($R$3)) -> 0.49390973 | N206: =IF(A206-7<$R$2,"",C206/INDEX(Clean_Data!$C$2:$C$4314,MATCH(A206-7,Clean_Data!$A$2:$A$4314,1))-1) -> 0.05075 | O206: =IF(A206-30<$R$2,"",C206/INDEX(Clean_Data!$C$2:$C$4314,MATCH(A206-30,Clean_Data!$A$2:$A$4314,1))-1) -> 0.1694026
A207: 42213 | B207: =YEAR(A207) -> 2015 | C207: 295.76 | D207: =A207-A206 -> 1 | E207: =LN(C207) -> 5.6895483 | F207: =LN(C207/C206) -> 0.0052545166 | G207: =IF(AND(D207=1,A207>=$R$2),F207,"") -> 0.0052545166 | H207: =IF(G207="","",G207^2) -> 2.7609944e-05 | I207: =IF(G207="","",C207/C206-1) -> 0.0052683457 | J207: =AVERAGE(C8:C207) -> 248.8495 | K207: =MAX(K206,C207) -> 378 | L207: =C207/K207-1 -> -0.21756614 | M207: =IF(COUNT(G178:G207)<20,"",_xlfn.STDEV.S(G178:G207)*SQRT($R$3)) -> 0.490889 | N207: =IF(A207-7<$R$2,"",C207/INDEX(Clean_Data!$C$2:$C$4314,MATCH(A207-7,Clean_Data!$A$2:$A$4314,1))-1) -> 0.066493581 | O207: =IF(A207-30<$R$2,"",C207/INDEX(Clean_Data!$C$2:$C$4314,MATCH(A207-30,Clean_Data!$A$2:$A$4314,1))-1) -> 0.18726667
A208: 42214 | B208: =YEAR(A208) -> 2015 | C208: 290.19 | D208: =A208-A207 -> 1 | E208: =LN(C208) -> 5.6705359 | F208: =LN(C208/C207) -> -0.019012434 | G208: =IF(AND(D208=1,A208>=$R$2),F208,"") -> -0.019012434 | H208: =IF(G208="","",G208^2) -> 0.00036147264 | I208: =IF(G208="","",C208/C207-1) -> -0.018832837 | J208: =AVERAGE(C9:C208) -> 248.49795 | K208: =MAX(K207,C208) -> 378 | L208: =C208/K208-1 -> -0.23230159 | M208: =IF(COUNT(G179:G208)<20,"",_xlfn.STDEV.S(G179:G208)*SQRT($R$3)) -> 0.48781737 | N208: =IF(A208-7<$R$2,"",C208/INDEX(Clean_Data!$C$2:$C$4314,MATCH(A208-7,Clean_Data!$A$2:$A$4314,1))-1) -> 0.044262118 | O208: =IF(A208-30<$R$2,"",C208/INDEX(Clean_Data!$C$2:$C$4314,MATCH(A208-30,Clean_Data!$A$2:$A$4314,1))-1) -> 0.12677642
A209: 42215 | B209: =YEAR(A209) -> 2015 | C209: 288.49 | D209: =A209-A208 -> 1 | E209: =LN(C209) -> 5.6646604 | F209: =LN(C209/C208) -> -0.0058754576 | G209: =IF(AND(D209=1,A209>=$R$2),F209,"") -> -0.0058754576 | H209: =IF(G209="","",G209^2) -> 3.4521002e-05 | I209: =IF(G209="","",C209/C208-1) -> -0.0058582308 | J209: =AVERAGE(C10:C209) -> 248.1904 | K209: =MAX(K208,C209) -> 378 | L209: =C209/K209-1 -> -0.23679894 | M209: =IF(COUNT(G180:G209)<20,"",_xlfn.STDEV.S(G180:G209)*SQRT($R$3)) -> 0.48344545 | N209: =IF(A209-7<$R$2,"",C209/INDEX(Clean_Data!$C$2:$C$4314,MATCH(A209-7,Clean_Data!$A$2:$A$4314,1))-1) -> 0.040015862 | O209: =IF(A209-30<$R$2,"",C209/INDEX(Clean_Data!$C$2:$C$4314,MATCH(A209-30,Clean_Data!$A$2:$A$4314,1))-1) -> 0.093510727
A210: 42216 | B210: =YEAR(A210) -> 2015 | C210: 285.19 | D210: =A210-A209 -> 1 | E210: =LN(C210) -> 5.6531556 | F210: =LN(C210/C209) -> -0.011504798 | G210: =IF(AND(D210=1,A210>=$R$2),F210,"") -> -0.011504798 | H210: =IF(G210="","",G210^2) -> 0.00013236039 | I210: =IF(G210="","",C210/C209-1) -> -0.011438871 | J210: =AVERAGE(C11:C210) -> 247.91635 | K210: =MAX(K209,C210) -> 378 | L210: =C210/K210-1 -> -0.2455291 | M210: =IF(COUNT(G181:G210)<20,"",_xlfn.STDEV.S(G181:G210)*SQRT($R$3)) -> 0.48021647 | N210: =IF(A210-7<$R$2,"",C210/INDEX(Clean_Data!$C$2:$C$4314,MATCH(A210-7,Clean_Data!$A$2:$A$4314,1))-1) -> -0.013592972 | O210: =IF(A210-30<$R$2,"",C210/INDEX(Clean_Data!$C$2:$C$4314,MATCH(A210-30,Clean_Data!$A$2:$A$4314,1))-1) -> 0.10103467
A211: 42217 | B211: =YEAR(A211) -> 2015 | C211: 281.53 | D211: =A211-A210 -> 1 | E211: =LN(C211) -> 5.640239 | F211: =LN(C211/C210) -> -0.012916611 | G211: =IF(AND(D211=1,A211>=$R$2),F211,"") -> -0.012916611 | H211: =IF(G211="","",G211^2) -> 0.00016683884 | I211: =IF(G211="","",C211/C210-1) -> -0.01283355 | J211: =AVERAGE(C12:C211) -> 247.87905 | K211: =MAX(K210,C211) -> 378 | L211: =C211/K211-1 -> -0.25521164 | M211: =IF(COUNT(G182:G211)<20,"",_xlfn.STDEV.S(G182:G211)*SQRT($R$3)) -> 0.4786649 | N211: =IF(A211-7<$R$2,"",C211/INDEX(Clean_Data!$C$2:$C$4314,MATCH(A211-7,Clean_Data!$A$2:$A$4314,1))-1) -> -0.028201588 | O211: =IF(A211-30<$R$2,"",C211/INDEX(Clean_Data!$C$2:$C$4314,MATCH(A211-30,Clean_Data!$A$2:$A$4314,1))-1) -> 0.10468903
A212: 42218 | B212: =YEAR(A212) -> 2015 | C212: 282.62 | D212: =A212-A211 -> 1 | E212: =LN(C212) -> 5.6441032 | F212: =LN(C212/C211) -> 0.0038642253 | G212: =IF(AND(D212=1,A212>=$R$2),F212,"") -> 0.0038642253 | H212: =IF(G212="","",G212^2) -> 1.4932237e-05 | I212: =IF(G212="","",C212/C211-1) -> 0.0038717011 | J212: =AVERAGE(C13:C212) -> 247.99215 | K212: =MAX(K211,C212) -> 378 | L212: =C212/K212-1 -> -0.25232804 | M212: =IF(COUNT(G183:G212)<20,"",_xlfn.STDEV.S(G183:G212)*SQRT($R$3)) -> 0.47834638 | N212: =IF(A212-7<$R$2,"",C212/INDEX(Clean_Data!$C$2:$C$4314,MATCH(A212-7,Clean_Data!$A$2:$A$4314,1))-1) -> -0.038347681 | O212: =IF(A212-30<$R$2,"",C212/INDEX(Clean_Data!$C$2:$C$4314,MATCH(A212-30,Clean_Data!$A$2:$A$4314,1))-1) -> 0.099902705
... A4314: 46321 | B4314: =YEAR(A4314) -> 2026 | C4314: 80056.43 | D4314: =A4314-A4313 -> 1 | E4314: =LN(C4314) -> 11.290487 | F4314: =LN(C4314/C4313) -> 0.0017758243 | G4314: =IF(AND(D4314=1,A4314>=$R$2),F4314,"") -> 0.0017758243 | H4314: =IF(G4314="","",G4314^2) -> 3.1535521e-06 | I4314: =IF(G4314="","",C4314/C4313-1) -> 0.001777402 | J4314: =AVERAGE(C4115:C4314) -> 72969.65 | K4314: =MAX(K4313,C4314) -> 124720.09 | L4314: =C4314/K4314-1 -> -0.35811119 | M4314: =IF(COUNT(G4285:G4314)<20,"",_xlfn.STDEV.S(G4285:G4314)*SQRT($R$3)) -> 0.25365255 | N4314: =IF(A4314-7<$R$2,"",C4314/INDEX(Clean_Data!$C$2:$C$4314,MATCH(A4314-7,Clean_Data!$A$2:$A$4314,1))-1) -> -0.021367079 | O4314: =IF(A4314-30<$R$2,"",C4314/INDEX(Clean_Data!$C$2:$C$4314,MATCH(A4314-30,Clean_Data!$A$2:$A$4314,1))-1) -> -0.050759592

Sheet Obj1_Value
A1: Objective 1: Long-term value trajectory and growth of Bitcoin (Dec 2014 - Oct 2026)
A2: RO1: To examine Bitcoin's long-run price trajectory, annual returns and compound growth in order to evaluate its value proposition for financial institutions and businesses.
A4: Table 1: Overall price growth and trend summary
A5: Measure | B5: Value | C5: Method (Excel formula logic)
A6: First observation date | B6: =MIN(Clean_Data!$A$2:$A$4314) -> 41974 | C6: MIN of dates
A7: Opening price (US$) | B7: =INDEX(Clean_Data!$C$2:$C$4314,MATCH(B6,Clean_Data!$A$2:$A$4314,0)) -> 370 | C7: INDEX/MATCH on first date
A8: Latest observation date | B8: =MAX(Clean_Data!$A$2:$A$4314) -> 46321 | C8: MAX of dates
A9: Latest price (US$) | B9: =INDEX(Clean_Data!$C$2:$C$4314,MATCH(B8,Clean_Data!$A$2:$A$4314,0)) -> 80056.43 | C9: INDEX/MATCH on last date
A10: Holding period (years) | B10: =(B8-B6)/365.25 -> 11.901437 | C10: (Last date - first date) / 365.25
A11: Total return | B11: =B9/B7-1 -> 215.36873 | C11: Latest / opening - 1
A12: Price multiple (x) | B12: =B9/B7 -> 216.36873 | C12: Latest / opening
A13: Compound annual growth rate (CAGR) | B13: =(B9/B7)^(1/B10)-1 -> 0.57112642 | C13: (Latest / opening)^(1/years) - 1
A14: Cumulative log return | B14: =SUM(Clean_Data!$F$3:$F$4314) -> 5.376984 | C14: SUM of all log returns = LN(latest/opening)
A15: Average daily price, full period (US$) | B15: =AVERAGE(Clean_Data!$C$2:$C$4314) -> 30788.072 | C15: AVERAGE of all daily prices
A16: All-time high, daily close (US$) | B16: =MAX(Clean_Data!$C$2:$C$4314) -> 124720.09 | C16: MAX of prices
A17: Date of all-time high | B17: =INDEX(Clean_Data!$A$2:$A$4314,MATCH(B16,Clean_Data!$C$2:$C$4314,0)) -> 45935 | C17: INDEX/MATCH
A18: Lowest daily price (US$) | B18: =MIN(Clean_Data!$C$2:$C$4314) -> 120 | C18: MIN of prices (14-Jan-2015 thin-market print)
A19: Date of lowest price | B19: =INDEX(Clean_Data!$A$2:$A$4314,MATCH(B18,Clean_Data!$C$2:$C$4314,0)) -> 42018 | C19: INDEX/MATCH
A20: Latest price vs all-time high | B20: =B9/B16-1 -> -0.35811119 | C20: Latest / ATH - 1
A21: Log-linear trend slope (per day) | B21: =SLOPE(Clean_Data!$E$2:$E$4314,Clean_Data!$A$2:$A$4314) -> 0.0013913087 | C21: SLOPE of LN(price) on date
A22: Implied annual trend growth rate | B22: =EXP(B21*365.25)-1 -> 0.66225567 | C22: EXP(slope x 365.25) - 1
A23: R-squared of log-linear trend | B23: =RSQ(Clean_Data!$E$2:$E$4314,Clean_Data!$A$2:$A$4314) -> 0.86167591 | C23: RSQ of LN(price) on date
A24: Source: Author's calculations in Microsoft Excel using FRED (2026) series CBBTCUSD. | M24: Source: Author's calculations using FRED (2026) series CBBTCUSD (Coinbase, daily close).
A26: Table 2: Annual price statistics, 2014-2026
A27: Year | B27: Observations | C27: Opening price (US$) | D27: Closing price (US$) | E27: Average price (US$) | F27: Minimum price (US$) | G27: Maximum price (US$) | H27: High / low ratio (x) | I27: Annual return | J27: Sum of log returns | K27: Note
A28: 2014 | B28: =COUNTIF(Clean_Data!$B$2:$B$4314,A28) -> 9 | C28: =INDEX(Clean_Data!$C$2:$C$4314,MATCH(A28,Clean_Data!$B$2:$B$4314,0)) -> 370 | D28: =INDEX(Clean_Data!$C$2:$C$4314,MATCH(A28,Clean_Data!$B$2:$B$4314,0)+B28-1) -> 340 | E28: =AVERAGEIFS(Clean_Data!$C$2:$C$4314,Clean_Data!$B$2:$B$4314,A28) -> 367.4 | F28: =_xlfn.MINIFS(Clean_Data!$C$2:$C$4314,Clean_Data!$B$2:$B$4314,A28) -> 340 | G28: =_xlfn.MAXIFS(Clean_Data!$C$2:$C$4314,Clean_Data!$B$2:$B$4314,A28) -> 378 | H28: =G28/F28 -> 1.1117647 | I28: n/a | J28: =SUMIFS(Clean_Data!$F$3:$F$4314,Clean_Data!$B$3:$B$4314,A28) -> -0.084557388 | K28: Partial year: December only
A29: 2015 | B29: =COUNTIF(Clean_Data!$B$2:$B$4314,A29) -> 353 | C29: =INDEX(Clean_Data!$C$2:$C$4314,MATCH(A29,Clean_Data!$B$2:$B$4314,0)) -> 288.99 | D29: =INDEX(Clean_Data!$C$2:$C$4314,MATCH(A29,Clean_Data!$B$2:$B$4314,0)+B29-1) -> 430.35 | E29: =AVERAGEIFS(Clean_Data!$C$2:$C$4314,Clean_Data!$B$2:$B$4314,A29) -> 272.86051 | F29: =_xlfn.MINIFS(Clean_Data!$C$2:$C$4314,Clean_Data!$B$2:$B$4314,A29) -> 120 | G29: =_xlfn.MAXIFS(Clean_Data!$C$2:$C$4314,Clean_Data!$B$2:$B$4314,A29) -> 464.27 | H29: =G29/F29 -> 3.8689167 | I29: =D29/D28-1 -> 0.26573529 | J29: =SUMIFS(Clean_Data!$F$3:$F$4314,Clean_Data!$B$3:$B$4314,A29) -> 0.23565321
A30: 2016 | B30: =COUNTIF(Clean_Data!$B$2:$B$4314,A30) -> 366 | C30: =INDEX(Clean_Data!$C$2:$C$4314,MATCH(A30,Clean_Data!$B$2:$B$4314,0)) -> 435.66 | D30: =INDEX(Clean_Data!$C$2:$C$4314,MATCH(A30,Clean_Data!$B$2:$B$4314,0)+B30-1) -> 973.37 | E30: =AVERAGEIFS(Clean_Data!$C$2:$C$4314,Clean_Data!$B$2:$B$4314,A30) -> 568.52765 | F30: =_xlfn.MINIFS(Clean_Data!$C$2:$C$4314,Clean_Data!$B$2:$B$4314,A30) -> 357.53 | G30: =_xlfn.MAXIFS(Clean_Data!$C$2:$C$4314,Clean_Data!$B$2:$B$4314,A30) -> 982.17 | H30: =G30/F30 -> 2.7470981 | I30: =D30/D29-1 -> 1.2618102 | J30: =SUMIFS(Clean_Data!$F$3:$F$4314,Clean_Data!$B$3:$B$4314,A30) -> 0.81616545
A31: 2017 | B31: =COUNTIF(Clean_Data!$B$2:$B$4314,A31) -> 365 | C31: =INDEX(Clean_Data!$C$2:$C$4314,MATCH(A31,Clean_Data!$B$2:$B$4314,0)) -> 992.95 | D31: =INDEX(Clean_Data!$C$2:$C$4314,MATCH(A31,Clean_Data!$B$2:$B$4314,0)+B31-1) -> 13863.13 | E31: =AVERAGEIFS(Clean_Data!$C$2:$C$4314,Clean_Data!$B$2:$B$4314,A31) -> 4004.8998 | F31: =_xlfn.MINIFS(Clean_Data!$C$2:$C$4314,Clean_Data!$B$2:$B$4314,A31) -> 795.77 | G31: =_xlfn.MAXIFS(Clean_Data!$C$2:$C$4314,Clean_Data!$B$2:$B$4314,A31) -> 19650.01 | H31: =G31/F31 -> 24.693077 | I31: =D31/D30-1 -> 13.242405 | J31: =SUMIFS(Clean_Data!$F$3:$F$4314,Clean_Data!$B$3:$B$4314,A31) -> 2.6562238
A32: 2018 | B32: =COUNTIF(Clean_Data!$B$2:$B$4314,A32) -> 365 | C32: =INDEX(Clean_Data!$C$2:$C$4314,MATCH(A32,Clean_Data!$B$2:$B$4314,0)) -> 13480.01 | D32: =INDEX(Clean_Data!$C$2:$C$4314,MATCH(A32,Clean_Data!$B$2:$B$4314,0)+B32-1) -> 3691.86 | E32: =AVERAGEIFS(Clean_Data!$C$2:$C$4314,Clean_Data!$B$2:$B$4314,A32) -> 7520.4663 | F32: =_xlfn.MINIFS(Clean_Data!$C$2:$C$4314,Clean_Data!$B$2:$B$4314,A32) -> 3183 | G32: =_xlfn.MAXIFS(Clean_Data!$C$2:$C$4314,Clean_Data!$B$2:$B$4314,A32) -> 17098.99 | H32: =G32/F32 -> 5.371973 | I32: =D32/D31-1 -> -0.73369217 | J32: =SUMIFS(Clean_Data!$F$3:$F$4314,Clean_Data!$B$3:$B$4314,A32) -> -1.3231024
A33: 2019 | B33: =COUNTIF(Clean_Data!$B$2:$B$4314,A33) -> 365 | C33: =INDEX(Clean_Data!$C$2:$C$4314,MATCH(A33,Clean_Data!$B$2:$B$4314,0)) -> 3826.1 | D33: =INDEX(Clean_Data!$C$2:$C$4314,MATCH(A33,Clean_Data!$B$2:$B$4314,0)+B33-1) -> 7158.01 | E33: =AVERAGEIFS(Clean_Data!$C$2:$C$4314,Clean_Data!$B$2:$B$4314,A33) -> 7365.9469 | F33: =_xlfn.MINIFS(Clean_Data!$C$2:$C$4314,Clean_Data!$B$2:$B$4314,A33) -> 3359 | G33: =_xlfn.MAXIFS(Clean_Data!$C$2:$C$4314,Clean_Data!$B$2:$B$4314,A33) -> 12902.52 | H33: =G33/F33 -> 3.8411789 | I33: =D33/D32-1 -> 0.9388628 | J33: =SUMIFS(Clean_Data!$F$3:$F$4314,Clean_Data!$B$3:$B$4314,A33) -> 0.66210161
A34: 2020 | B34: =COUNTIF(Clean_Data!$B$2:$B$4314,A34) -> 365 | C34: =INDEX(Clean_Data!$C$2:$C$4314,MATCH(A34,Clean_Data!$B$2:$B$4314,0)) -> 7174.32 | D34: =INDEX(Clean_Data!$C$2:$C$4314,MATCH(A34,Clean_Data!$B$2:$B$4314,0)+B34-1) -> 29026.97 | E34: =AVERAGEIFS(Clean_Data!$C$2:$C$4314,Clean_Data!$B$2:$B$4314,A34) -> 11121.467 | F34: =_xlfn.MINIFS(Clean_Data!$C$2:$C$4314,Clean_Data!$B$2:$B$4314,A34) -> 4980 | G34: =_xlfn.MAXIFS(Clean_Data!$C$2:$C$4314,Clean_Data!$B$2:$B$4314,A34) -> 29026.97 | H34: =G34/F34 -> 5.8287088 | I34: =D34/D33-1 -> 3.0551732 | J34: =SUMIFS(Clean_Data!$F$3:$F$4314,Clean_Data!$B$3:$B$4314,A34) -> 1.3999934
A35: 2021 | B35: =COUNTIF(Clean_Data!$B$2:$B$4314,A35) -> 365 | C35: =INDEX(Clean_Data!$C$2:$C$4314,MATCH(A35,Clean_Data!$B$2:$B$4314,0)) -> 29391.09 | D35: =INDEX(Clean_Data!$C$2:$C$4314,MATCH(A35,Clean_Data!$B$2:$B$4314,0)+B35-1) -> 46244.63 | E35: =AVERAGEIFS(Clean_Data!$C$2:$C$4314,Clean_Data!$B$2:$B$4314,A35) -> 47440.638 | F35: =_xlfn.MINIFS(Clean_Data!$C$2:$C$4314,Clean_Data!$B$2:$B$4314,A35) -> 29391.09 | G35: =_xlfn.MAXIFS(Clean_Data!$C$2:$C$4314,Clean_Data!$B$2:$B$4314,A35) -> 67510.06 | H35: =G35/F35 -> 2.2969567 | I35: =D35/D34-1 -> 0.59316077 | J35: =SUMIFS(Clean_Data!$F$3:$F$4314,Clean_Data!$B$3:$B$4314,A35) -> 0.46571995
A36: 2022 | B36: =COUNTIF(Clean_Data!$B$2:$B$4314,A36) -> 365 | C36: =INDEX(Clean_Data!$C$2:$C$4314,MATCH(A36,Clean_Data!$B$2:$B$4314,0)) -> 47748.83 | D36: =INDEX(Clean_Data!$C$2:$C$4314,MATCH(A36,Clean_Data!$B$2:$B$4314,0)+B36-1) -> 16531 | E36: =AVERAGEIFS(Clean_Data!$C$2:$C$4314,Clean_Data!$B$2:$B$4314,A36) -> 28183.65 | F36: =_xlfn.MINIFS(Clean_Data!$C$2:$C$4314,Clean_Data!$B$2:$B$4314,A36) -> 15755.75 | G36: =_xlfn.MAXIFS(Clean_Data!$C$2:$C$4314,Clean_Data!$B$2:$B$4314,A36) -> 47748.83 | H36: =G36/F36 -> 3.0305653 | I36: =D36/D35-1 -> -0.64253147 | J36: =SUMIFS(Clean_Data!$F$3:$F$4314,Clean_Data!$B$3:$B$4314,A36) -> -1.0287079
A37: 2023 | B37: =COUNTIF(Clean_Data!$B$2:$B$4314,A37) -> 365 | C37: =INDEX(Clean_Data!$C$2:$C$4314,MATCH(A37,Clean_Data!$B$2:$B$4314,0)) -> 16615.18 | D37: =INDEX(Clean_Data!$C$2:$C$4314,MATCH(A37,Clean_Data!$B$2:$B$4314,0)+B37-1) -> 42300.78 | E37: =AVERAGEIFS(Clean_Data!$C$2:$C$4314,Clean_Data!$B$2:$B$4314,A37) -> 28858.015 | F37: =_xlfn.MINIFS(Clean_Data!$C$2:$C$4314,Clean_Data!$B$2:$B$4314,A37) -> 16615.18 | G37: =_xlfn.MAXIFS(Clean_Data!$C$2:$C$4314,Clean_Data!$B$2:$B$4314,A37) -> 44223.94 | H37: =G37/F37 -> 2.6616588 | I37: =D37/D36-1 -> 1.5588761 | J37: =SUMIFS(Clean_Data!$F$3:$F$4314,Clean_Data!$B$3:$B$4314,A37) -> 0.93956812
A38: 2024 | B38: =COUNTIF(Clean_Data!$B$2:$B$4314,A38) -> 366 | C38: =INDEX(Clean_Data!$C$2:$C$4314,MATCH(A38,Clean_Data!$B$2:$B$4314,0)) -> 44229.57 | D38: =INDEX(Clean_Data!$C$2:$C$4314,MATCH(A38,Clean_Data!$B$2:$B$4314,0)+B38-1) -> 94383.59 | E38: =AVERAGEIFS(Clean_Data!$C$2:$C$4314,Clean_Data!$B$2:$B$4314,A38) -> 66075.075 | F38: =_xlfn.MINIFS(Clean_Data!$C$2:$C$4314,Clean_Data!$B$2:$B$4314,A38) -> 39547.64 | G38: =_xlfn.MAXIFS(Clean_Data!$C$2:$C$4314,Clean_Data!$B$2:$B$4314,A38) -> 106136.99 | H38: =G38/F38 -> 2.6837756 | I38: =D38/D37-1 -> 1.2312494 | J38: =SUMIFS(Clean_Data!$F$3:$F$4314,Clean_Data!$B$3:$B$4314,A38) -> 0.8025617
A39: 2025 | B39: =COUNTIF(Clean_Data!$B$2:$B$4314,A39) -> 365 | C39: =INDEX(Clean_Data!$C$2:$C$4314,MATCH(A39,Clean_Data!$B$2:$B$4314,0)) -> 96903.19 | D39: =INDEX(Clean_Data!$C$2:$C$4314,MATCH(A39,Clean_Data!$B$2:$B$4314,0)+B39-1) -> 87696 | E39: =AVERAGEIFS(Clean_Data!$C$2:$C$4314,Clean_Data!$B$2:$B$4314,A39) -> 101648.72 | F39: =_xlfn.MINIFS(Clean_Data!$C$2:$C$4314,Clean_Data!$B$2:$B$4314,A39) -> 76251.64 | G39: =_xlfn.MAXIFS(Clean_Data!$C$2:$C$4314,Clean_Data!$B$2:$B$4314,A39) -> 124720.09 | H39: =G39/F39 -> 1.6356381 | I39: =D39/D38-1 -> -0.070855432 | J39: =SUMIFS(Clean_Data!$F$3:$F$4314,Clean_Data!$B$3:$B$4314,A39) -> -0.073490935
A40: 2026 | B40: =COUNTIF(Clean_Data!$B$2:$B$4314,A40) -> 299 | C40: =INDEX(Clean_Data!$C$2:$C$4314,MATCH(A40,Clean_Data!$B$2:$B$4314,0)) -> 88642.88 | D40: =INDEX(Clean_Data!$C$2:$C$4314,MATCH(A40,Clean_Data!$B$2:$B$4314,0)+B40-1) -> 80056.43 | E40: =AVERAGEIFS(Clean_Data!$C$2:$C$4314,Clean_Data!$B$2:$B$4314,A40) -> 73930.702 | F40: =_xlfn.MINIFS(Clean_Data!$C$2:$C$4314,Clean_Data!$B$2:$B$4314,A40) -> 58585.96 | G40: =_xlfn.MAXIFS(Clean_Data!$C$2:$C$4314,Clean_Data!$B$2:$B$4314,A40) -> 96852.91 | H40: =G40/F40 -> 1.6531761 | I40: =D40/D39-1 -> -0.087114236 | J40: =SUMIFS(Clean_Data!$F$3:$F$4314,Clean_Data!$B$3:$B$4314,A40) -> -0.091144527 | K40: Partial year: to 26-Oct (YTD)
A41: Total / overall | B41: =SUM(B28:B40) -> 4313 | E41: =AVERAGE(Clean_Data!$C$2:$C$4314) -> 30788.072 | F41: =MIN(F28:F40) -> 120 | G41: =MAX(G28:G40) -> 124720.09 | J41: =SUM(J28:J40) -> 5.376984
A43: Mean annual return, 2015-2025 (full years) | B43: =AVERAGE(I29:I39) -> 1.8818358
A44: Median annual return, 2015-2025 | B44: =MEDIAN(I29:I39) -> 0.9388628
A45: Best calendar year return | B45: =MAX(I29:I39) -> 13.242405
A46: Worst calendar year return | B46: =MIN(I29:I39) -> -0.73369217 | M46: Note: 2014 = December only; 2026 = year to 26 October. Source: Table 2.
A47: Number of positive years (of 11) | B47: =COUNTIF(I29:I39,">0") -> 8
A48: Number of negative years (of 11) | B48: =COUNTIF(I29:I39,"<0") -> 3
A49: Note: Annual return = closing price / previous year's closing price - 1. Source: Author's calculations using FRED (2026).
M68: Source: Table 2 (closing price / previous closing price - 1).

Sheet Obj2_Volatility
A1: Objective 2: Magnitude, distribution and evolution of Bitcoin's price volatility
A2: RO2: To measure the scale and distribution of Bitcoin's daily return volatility and test whether volatility has declined as the market has matured and institutional access has expanded.
A4: Table 3: Descriptive statistics of daily log returns (20-Jan-2015 to 26-Oct-2026)
A5: Statistic | B5: Value | C5: Method (Excel formula logic)
A6: Sample start | B6: =Clean_Data!$R$2 -> 42024 | C6: Input on Clean_Data
A7: Sample end | B7: =MAX(Clean_Data!$A$2:$A$4314) -> 46321 | C7: MAX of dates
A8: Number of daily returns (N) | B8: =COUNT(Clean_Data!$G$2:$G$4314) -> 4296 | C8: COUNT
A9: Mean daily log return | B9: =AVERAGE(Clean_Data!$G$2:$G$4314) -> 0.0013685457 | C9: AVERAGE
A10: Median daily log return | B10: =MEDIAN(Clean_Data!$G$2:$G$4314) -> 0.00093526378 | C10: MEDIAN
A11: Standard deviation (daily) | B11: =_xlfn.STDEV.S(Clean_Data!$G$2:$G$4314) -> 0.03456091 | C11: STDEV.S (sample)
A12: Minimum daily return | B12: =MIN(Clean_Data!$G$2:$G$4314) -> -0.46862467 | C12: MIN
A13: Maximum daily return | B13: =MAX(Clean_Data!$G$2:$G$4314) -> 0.24060603 | C13: MAX
A14: Annualised mean return | B14: =B9*Clean_Data!$R$3 -> 0.49951917 | C14: Mean x 365
A15: Annualised volatility | B15: =B11*SQRT(Clean_Data!$R$3) -> 0.66028526 | C15: SD x SQRT(365)
A16: Coefficient of variation | B16: =B11/B9 -> 25.25375 | C16: SD / mean
A17: Skewness | B17: =SKEW(Clean_Data!$G$2:$G$4314) -> -0.59894125 | C17: SKEW
A18: Excess kurtosis | B18: =KURT(Clean_Data!$G$2:$G$4314) -> 11.958703 | C18: KURT (normal = 0)
A19: Jarque-Bera statistic | B19: =B8/6*(B17^2+B18^2/4) -> 25855.745 | C19: N/6 x (S^2 + K^2/4)
A20: JB critical value (5%, 2 df) | B20: =_xlfn.CHISQ.INV.RT(0.05,2) -> 5.9914645 | C20: CHISQ.INV.RT(0.05, 2)
A21: JB p-value | B21: =_xlfn.CHISQ.DIST.RT(B19,2) -> 0 | C21: CHISQ.DIST.RT(JB, 2)
A22: Normality decision (5% level) | B22: =IF(B21<0.05,"Reject normality","Do not reject") -> Reject normality | C22: IF p < 0.05
A23: Share of positive days | B23: =COUNTIF(Clean_Data!$G$2:$G$4314,">0")/B8 -> 0.5211825 | C23: COUNTIF(>0) / N
A24: Extreme-move threshold (absolute daily return) | B24: 0.05 | C24: Input | L24: Source: Table 4 (daily SD x SQRT(365)); 2026 to 26 October.
A25: Days beyond threshold: observed | B25: =COUNTIF(Clean_Data!$G$2:$G$4314,">"&B24)+COUNTIF(Clean_Data!$G$2:$G$4314,"<"&-B24) -> 495 | C25: COUNTIF(>x) + COUNTIF(<-x)
A26: Days beyond threshold: expected if normal | B26: =B8*(_xlfn.NORM.DIST(-B24,B9,B11,TRUE())+1-_xlfn.NORM.DIST(B24,B9,B11,TRUE())) -> 637.06584 | C26: N x tail probability of NORM.DIST
A27: Fat-tail ratio (observed / normal) | B27: =B25/B26 -> 0.77699975 | C27: Observed / expected
A28: Second threshold (absolute daily return) | B28: 0.1 | C28: Input
A29: Days beyond threshold: observed | B29: =COUNTIF(Clean_Data!$G$2:$G$4314,">"&B28)+COUNTIF(Clean_Data!$G$2:$G$4314,"<"&-B28) -> 93 | C29: COUNTIF(>x) + COUNTIF(<-x)
A30: Days beyond threshold: expected if normal | B30: =B8*(_xlfn.NORM.DIST(-B28,B9,B11,TRUE())+1-_xlfn.NORM.DIST(B28,B9,B11,TRUE())) -> 16.487988 | C30: N x tail probability of NORM.DIST
A31: Fat-tail ratio (observed / normal) | B31: =B29/B30 -> 5.6404701 | C31: Observed / expected
A32: Source: Author's calculations using FRED (2026). Log return = LN(Pt / Pt-1); consecutive calendar days only.
A34: Table 4: Annual volatility profile of daily log returns, 2015-2026
A35: Year | B35: N (days) | C35: Mean daily log return | D35: Daily standard deviation | E35: Annualised volatility | F35: Largest daily gain | G35: Largest daily loss | H35: Days with |return| > 5% | I35: % of days with |return| > 5% | J35: Share of up days
A36: 2015 | B36: =COUNTIFS(Clean_Data!$B$2:$B$4314,A36,Clean_Data!$G$2:$G$4314,">=-10") -> 346 | C36: =AVERAGEIFS(Clean_Data!$G$2:$G$4314,Clean_Data!$B$2:$B$4314,A36,Clean_Data!$G$2:$G$4314,">=-10") -> 0.0018677293 | D36: =SQRT((SUMIFS(Clean_Data!$H$2:$H$4314,Clean_Data!$B$2:$B$4314,A36,Clean_Data!$G$2:$G$4314,">=-10")-B36*C36^2)/(B36-1)) -> 0.029927909 | E36: =D36*SQRT(Clean_Data!$R$3) -> 0.5717719 | F36: =_xlfn.MAXIFS(Clean_Data!$G$2:$G$4314,Clean_Data!$B$2:$B$4314,A36,Clean_Data!$G$2:$G$4314,">=-10") -> 0.10301758 | G36: =_xlfn.MINIFS(Clean_Data!$G$2:$G$4314,Clean_Data!$B$2:$B$4314,A36,Clean_Data!$G$2:$G$4314,">=-10") -> -0.14764925 | H36: =COUNTIFS(Clean_Data!$B$2:$B$4314,A36,Clean_Data!$G$2:$G$4314,">"&$B$24)+COUNTIFS(Clean_Data!$B$2:$B$4314,A36,Clean_Data!$G$2:$G$4314,"<"&-$B$24) -> 31 | I36: =H36/B36 -> 0.089595376 | J36: =COUNTIFS(Clean_Data!$B$2:$B$4314,A36,Clean_Data!$G$2:$G$4314,">0")/B36 -> 0.51734104
A37: 2016 | B37: =COUNTIFS(Clean_Data!$B$2:$B$4314,A37,Clean_Data!$G$2:$G$4314,">=-10") -> 366 | C37: =AVERAGEIFS(Clean_Data!$G$2:$G$4314,Clean_Data!$B$2:$B$4314,A37,Clean_Data!$G$2:$G$4314,">=-10") -> 0.0022299602 | D37: =SQRT((SUMIFS(Clean_Data!$H$2:$H$4314,Clean_Data!$B$2:$B$4314,A37,Clean_Data!$G$2:$G$4314,">=-10")-B37*C37^2)/(B37-1)) -> 0.026107406 | E37: =D37*SQRT(Clean_Data!$R$3) -> 0.4987813 | F37: =_xlfn.MAXIFS(Clean_Data!$G$2:$G$4314,Clean_Data!$B$2:$B$4314,A37,Clean_Data!$G$2:$G$4314,">=-10") -> 0.1091267 | G37: =_xlfn.MINIFS(Clean_Data!$G$2:$G$4314,Clean_Data!$B$2:$B$4314,A37,Clean_Data!$G$2:$G$4314,">=-10") -> -0.1846357 | H37: =COUNTIFS(Clean_Data!$B$2:$B$4314,A37,Clean_Data!$G$2:$G$4314,">"&$B$24)+COUNTIFS(Clean_Data!$B$2:$B$4314,A37,Clean_Data!$G$2:$G$4314,"<"&-$B$24) -> 24 | I37: =H37/B37 -> 0.06557377 | J37: =COUNTIFS(Clean_Data!$B$2:$B$4314,A37,Clean_Data!$G$2:$G$4314,">0")/B37 -> 0.56830601
A38: 2017 | B38: =COUNTIFS(Clean_Data!$B$2:$B$4314,A38,Clean_Data!$G$2:$G$4314,">=-10") -> 365 | C38: =AVERAGEIFS(Clean_Data!$G$2:$G$4314,Clean_Data!$B$2:$B$4314,A38,Clean_Data!$G$2:$G$4314,">=-10") -> 0.0072773255 | D38: =SQRT((SUMIFS(Clean_Data!$H$2:$H$4314,Clean_Data!$B$2:$B$4314,A38,Clean_Data!$G$2:$G$4314,">=-10")-B38*C38^2)/(B38-1)) -> 0.048753828 | E38: =D38*SQRT(Clean_Data!$R$3) -> 0.93144058 | F38: =_xlfn.MAXIFS(Clean_Data!$G$2:$G$4314,Clean_Data!$B$2:$B$4314,A38,Clean_Data!$G$2:$G$4314,">=-10") -> 0.24060603 | G38: =_xlfn.MINIFS(Clean_Data!$G$2:$G$4314,Clean_Data!$B$2:$B$4314,A38,Clean_Data!$G$2:$G$4314,">=-10") -> -0.17067595 | H38: =COUNTIFS(Clean_Data!$B$2:$B$4314,A38,Clean_Data!$G$2:$G$4314,">"&$B$24)+COUNTIFS(Clean_Data!$B$2:$B$4314,A38,Clean_Data!$G$2:$G$4314,"<"&-$B$24) -> 86 | I38: =H38/B38 -> 0.23561644 | J38: =COUNTIFS(Clean_Data!$B$2:$B$4314,A38,Clean_Data!$G$2:$G$4314,">0")/B38 -> 0.6
A39: 2018 | B39: =COUNTIFS(Clean_Data!$B$2:$B$4314,A39,Clean_Data!$G$2:$G$4314,">=-10") -> 365 | C39: =AVERAGEIFS(Clean_Data!$G$2:$G$4314,Clean_Data!$B$2:$B$4314,A39,Clean_Data!$G$2:$G$4314,">=-10") -> -0.0036249381 | D39: =SQRT((SUMIFS(Clean_Data!$H$2:$H$4314,Clean_Data!$B$2:$B$4314,A39,Clean_Data!$G$2:$G$4314,">=-10")-B39*C39^2)/(B39-1)) -> 0.043819945 | E39: =D39*SQRT(Clean_Data!$R$3) -> 0.83717888 | F39: =_xlfn.MAXIFS(Clean_Data!$G$2:$G$4314,Clean_Data!$B$2:$B$4314,A39,Clean_Data!$G$2:$G$4314,">=-10") -> 0.13115351 | G39: =_xlfn.MINIFS(Clean_Data!$G$2:$G$4314,Clean_Data!$B$2:$B$4314,A39,Clean_Data!$G$2:$G$4314,">=-10") -> -0.16793976 | H39: =COUNTIFS(Clean_Data!$B$2:$B$4314,A39,Clean_Data!$G$2:$G$4314,">"&$B$24)+COUNTIFS(Clean_Data!$B$2:$B$4314,A39,Clean_Data!$G$2:$G$4314,"<"&-$B$24) -> 77 | I39: =H39/B39 -> 0.2109589 | J39: =COUNTIFS(Clean_Data!$B$2:$B$4314,A39,Clean_Data!$G$2:$G$4314,">0")/B39 -> 0.49589041
A40: 2019 | B40: =COUNTIFS(Clean_Data!$B$2:$B$4314,A40,Clean_Data!$G$2:$G$4314,">=-10") -> 365 | C40: =AVERAGEIFS(Clean_Data!$G$2:$G$4314,Clean_Data!$B$2:$B$4314,A40,Clean_Data!$G$2:$G$4314,">=-10") -> 0.001813977 | D40: =SQRT((SUMIFS(Clean_Data!$H$2:$H$4314,Clean_Data!$B$2:$B$4314,A40,Clean_Data!$G$2:$G$4314,">=-10")-B40*C40^2)/(B40-1)) -> 0.036868196 | E40: =D40*SQRT(Clean_Data!$R$3) -> 0.70436589 | F40: =_xlfn.MAXIFS(Clean_Data!$G$2:$G$4314,Clean_Data!$B$2:$B$4314,A40,Clean_Data!$G$2:$G$4314,">=-10") -> 0.16965812 | G40: =_xlfn.MINIFS(Clean_Data!$G$2:$G$4314,Clean_Data!$B$2:$B$4314,A40,Clean_Data!$G$2:$G$4314,">=-10") -> -0.14801211 | H40: =COUNTIFS(Clean_Data!$B$2:$B$4314,A40,Clean_Data!$G$2:$G$4314,">"&$B$24)+COUNTIFS(Clean_Data!$B$2:$B$4314,A40,Clean_Data!$G$2:$G$4314,"<"&-$B$24) -> 46 | I40: =H40/B40 -> 0.1260274 | J40: =COUNTIFS(Clean_Data!$B$2:$B$4314,A40,Clean_Data!$G$2:$G$4314,">0")/B40 -> 0.52054795
A41: 2020 | B41: =COUNTIFS(Clean_Data!$B$2:$B$4314,A41,Clean_Data!$G$2:$G$4314,">=-10") -> 364 | C41: =AVERAGEIFS(Clean_Data!$G$2:$G$4314,Clean_Data!$B$2:$B$4314,A41,Clean_Data!$G$2:$G$4314,">=-10") -> 0.0038657775 | D41: =SQRT((SUMIFS(Clean_Data!$H$2:$H$4314,Clean_Data!$B$2:$B$4314,A41,Clean_Data!$G$2:$G$4314,">=-10")-B41*C41^2)/(B41-1)) -> 0.041490322 | E41: =D41*SQRT(Clean_Data!$R$3) -> 0.79267148 | F41: =_xlfn.MAXIFS(Clean_Data!$G$2:$G$4314,Clean_Data!$B$2:$B$4314,A41,Clean_Data!$G$2:$G$4314,">=-10") -> 0.13643524 | G41: =_xlfn.MINIFS(Clean_Data!$G$2:$G$4314,Clean_Data!$B$2:$B$4314,A41,Clean_Data!$G$2:$G$4314,">=-10") -> -0.46862467 | H41: =COUNTIFS(Clean_Data!$B$2:$B$4314,A41,Clean_Data!$G$2:$G$4314,">"&$B$24)+COUNTIFS(Clean_Data!$B$2:$B$4314,A41,Clean_Data!$G$2:$G$4314,"<"&-$B$24) -> 44 | I41: =H41/B41 -> 0.12087912 | J41: =COUNTIFS(Clean_Data!$B$2:$B$4314,A41,Clean_Data!$G$2:$G$4314,">0")/B41 -> 0.57142857
A42: 2021 | B42: =COUNTIFS(Clean_Data!$B$2:$B$4314,A42,Clean_Data!$G$2:$G$4314,">=-10") -> 365 | C42: =AVERAGEIFS(Clean_Data!$G$2:$G$4314,Clean_Data!$B$2:$B$4314,A42,Clean_Data!$G$2:$G$4314,">=-10") -> 0.0012759451 | D42: =SQRT((SUMIFS(Clean_Data!$H$2:$H$4314,Clean_Data!$B$2:$B$4314,A42,Clean_Data!$G$2:$G$4314,">=-10")-B42*C42^2)/(B42-1)) -> 0.042161732 | E42: =D42*SQRT(Clean_Data!$R$3) -> 0.80549875 | F42: =_xlfn.MAXIFS(Clean_Data!$G$2:$G$4314,Clean_Data!$B$2:$B$4314,A42,Clean_Data!$G$2:$G$4314,">=-10") -> 0.18249194 | G42: =_xlfn.MINIFS(Clean_Data!$G$2:$G$4314,Clean_Data!$B$2:$B$4314,A42,Clean_Data!$G$2:$G$4314,">=-10") -> -0.14897169 | H42: =COUNTIFS(Clean_Data!$B$2:$B$4314,A42,Clean_Data!$G$2:$G$4314,">"&$B$24)+COUNTIFS(Clean_Data!$B$2:$B$4314,A42,Clean_Data!$G$2:$G$4314,"<"&-$B$24) -> 75 | I42: =H42/B42 -> 0.20547945 | J42: =COUNTIFS(Clean_Data!$B$2:$B$4314,A42,Clean_Data!$G$2:$G$4314,">0")/B42 -> 0.50410959
A43: 2022 | B43: =COUNTIFS(Clean_Data!$B$2:$B$4314,A43,Clean_Data!$G$2:$G$4314,">=-10") -> 365 | C43: =AVERAGEIFS(Clean_Data!$G$2:$G$4314,Clean_Data!$B$2:$B$4314,A43,Clean_Data!$G$2:$G$4314,">=-10") -> -0.0028183779 | D43: =SQRT((SUMIFS(Clean_Data!$H$2:$H$4314,Clean_Data!$B$2:$B$4314,A43,Clean_Data!$G$2:$G$4314,">=-10")-B43*C43^2)/(B43-1)) -> 0.033742976 | E43: =D43*SQRT(Clean_Data!$R$3) -> 0.64465865 | F43: =_xlfn.MAXIFS(Clean_Data!$G$2:$G$4314,Clean_Data!$B$2:$B$4314,A43,Clean_Data!$G$2:$G$4314,">=-10") -> 0.13631974 | G43: =_xlfn.MINIFS(Clean_Data!$G$2:$G$4314,Clean_Data!$B$2:$B$4314,A43,Clean_Data!$G$2:$G$4314,">=-10") -> -0.17609878 | H43: =COUNTIFS(Clean_Data!$B$2:$B$4314,A43,Clean_Data!$G$2:$G$4314,">"&$B$24)+COUNTIFS(Clean_Data!$B$2:$B$4314,A43,Clean_Data!$G$2:$G$4314,"<"&-$B$24) -> 37 | I43: =H43/B43 -> 0.10136986 | J43: =COUNTIFS(Clean_Data!$B$2:$B$4314,A43,Clean_Data!$G$2:$G$4314,">0")/B43 -> 0.4630137
A44: 2023 | B44: =COUNTIFS(Clean_Data!$B$2:$B$4314,A44,Clean_Data!$G$2:$G$4314,">=-10") -> 365 | C44: =AVERAGEIFS(Clean_Data!$G$2:$G$4314,Clean_Data!$B$2:$B$4314,A44,Clean_Data!$G$2:$G$4314,">=-10") -> 0.0025741592 | D44: =SQRT((SUMIFS(Clean_Data!$H$2:$H$4314,Clean_Data!$B$2:$B$4314,A44,Clean_Data!$G$2:$G$4314,">=-10")-B44*C44^2)/(B44-1)) -> 0.022921716 | E44: =D44*SQRT(Clean_Data!$R$3) -> 0.43791878 | F44: =_xlfn.MAXIFS(Clean_Data!$G$2:$G$4314,Clean_Data!$B$2:$B$4314,A44,Clean_Data!$G$2:$G$4314,">=-10") -> 0.098938875 | G44: =_xlfn.MINIFS(Clean_Data!$G$2:$G$4314,Clean_Data!$B$2:$B$4314,A44,Clean_Data!$G$2:$G$4314,">=-10") -> -0.075751485 | H44: =COUNTIFS(Clean_Data!$B$2:$B$4314,A44,Clean_Data!$G$2:$G$4314,">"&$B$24)+COUNTIFS(Clean_Data!$B$2:$B$4314,A44,Clean_Data!$G$2:$G$4314,"<"&-$B$24) -> 22 | I44: =H44/B44 -> 0.060273973 | J44: =COUNTIFS(Clean_Data!$B$2:$B$4314,A44,Clean_Data!$G$2:$G$4314,">0")/B44 -> 0.50410959
A45: 2024 | B45: =COUNTIFS(Clean_Data!$B$2:$B$4314,A45,Clean_Data!$G$2:$G$4314,">=-10") -> 366 | C45: =AVERAGEIFS(Clean_Data!$G$2:$G$4314,Clean_Data!$B$2:$B$4314,A45,Clean_Data!$G$2:$G$4314,">=-10") -> 0.0021927915 | D45: =SQRT((SUMIFS(Clean_Data!$H$2:$H$4314,Clean_Data!$B$2:$B$4314,A45,Clean_Data!$G$2:$G$4314,">=-10")-B45*C45^2)/(B45-1)) -> 0.027717623 | E45: =D45*SQRT(Clean_Data!$R$3) -> 0.52954445 | F45: =_xlfn.MAXIFS(Clean_Data!$G$2:$G$4314,Clean_Data!$B$2:$B$4314,A45,Clean_Data!$G$2:$G$4314,">=-10") -> 0.11221959 | G45: =_xlfn.MINIFS(Clean_Data!$G$2:$G$4314,Clean_Data!$B$2:$B$4314,A45,Clean_Data!$G$2:$G$4314,">=-10") -> -0.08634012 | H45: =COUNTIFS(Clean_Data!$B$2:$B$4314,A45,Clean_Data!$G$2:$G$4314,">"&$B$24)+COUNTIFS(Clean_Data!$B$2:$B$4314,A45,Clean_Data!$G$2:$G$4314,"<"&-$B$24) -> 26 | I45: =H45/B45 -> 0.071038251 | J45: =COUNTIFS(Clean_Data!$B$2:$B$4314,A45,Clean_Data!$G$2:$G$4314,">0")/B45 -> 0.53005464
A46: 2025 | B46: =COUNTIFS(Clean_Data!$B$2:$B$4314,A46,Clean_Data!$G$2:$G$4314,">=-10") -> 365 | C46: =AVERAGEIFS(Clean_Data!$G$2:$G$4314,Clean_Data!$B$2:$B$4314,A46,Clean_Data!$G$2:$G$4314,">=-10") -> -0.00020134503 | D46: =SQRT((SUMIFS(Clean_Data!$H$2:$H$4314,Clean_Data!$B$2:$B$4314,A46,Clean_Data!$G$2:$G$4314,">=-10")-B46*C46^2)/(B46-1)) -> 0.021932411 | E46: =D46*SQRT(Clean_Data!$R$3) -> 0.41901813 | F46: =_xlfn.MAXIFS(Clean_Data!$G$2:$G$4314,Clean_Data!$B$2:$B$4314,A46,Clean_Data!$G$2:$G$4314,">=-10") -> 0.091549645 | G46: =_xlfn.MINIFS(Clean_Data!$G$2:$G$4314,Clean_Data!$B$2:$B$4314,A46,Clean_Data!$G$2:$G$4314,">=-10") -> -0.089896257 | H46: =COUNTIFS(Clean_Data!$B$2:$B$4314,A46,Clean_Data!$G$2:$G$4314,">"&$B$24)+COUNTIFS(Clean_Data!$B$2:$B$4314,A46,Clean_Data!$G$2:$G$4314,"<"&-$B$24) -> 14 | I46: =H46/B46 -> 0.038356164 | J46: =COUNTIFS(Clean_Data!$B$2:$B$4314,A46,Clean_Data!$G$2:$G$4314,">0")/B46 -> 0.49863014 | L46: Source: Clean_Data column M (STDEV.S of 30 daily log returns x SQRT(365)).
A47: 2026 | B47: =COUNTIFS(Clean_Data!$B$2:$B$4314,A47,Clean_Data!$G$2:$G$4314,">=-10") -> 299 | C47: =AVERAGEIFS(Clean_Data!$G$2:$G$4314,Clean_Data!$B$2:$B$4314,A47,Clean_Data!$G$2:$G$4314,">=-10") -> -0.00030483119 | D47: =SQRT((SUMIFS(Clean_Data!$H$2:$H$4314,Clean_Data!$B$2:$B$4314,A47,Clean_Data!$G$2:$G$4314,">=-10")-B47*C47^2)/(B47-1)) -> 0.02220019 | E47: =D47*SQRT(Clean_Data!$R$3) -> 0.42413404 | F47: =_xlfn.MAXIFS(Clean_Data!$G$2:$G$4314,Clean_Data!$B$2:$B$4314,A47,Clean_Data!$G$2:$G$4314,">=-10") -> 0.091109621 | G47: =_xlfn.MINIFS(Clean_Data!$G$2:$G$4314,Clean_Data!$B$2:$B$4314,A47,Clean_Data!$G$2:$G$4314,">=-10") -> -0.13198078 | H47: =COUNTIFS(Clean_Data!$B$2:$B$4314,A47,Clean_Data!$G$2:$G$4314,">"&$B$24)+COUNTIFS(Clean_Data!$B$2:$B$4314,A47,Clean_Data!$G$2:$G$4314,"<"&-$B$24) -> 13 | I47: =H47/B47 -> 0.043478261 | J47: =COUNTIFS(Clean_Data!$B$2:$B$4314,A47,Clean_Data!$G$2:$G$4314,">0")/B47 -> 0.47157191
A48: Full sample | B48: =SUM(B36:B47) -> 4296 | C48: =AVERAGE(Clean_Data!$G$2:$G$4314) -> 0.0013685457 | D48: =SQRT((SUM(Clean_Data!$H$2:$H$4314)-B48*C48^2)/(B48-1)) -> 0.03456091 | E48: =D48*SQRT(Clean_Data!$R$3) -> 0.66028526 | F48: =MAX(F36:F47) -> 0.24060603 | G48: =MIN(G36:G47) -> -0.46862467 | H48: =SUM(H36:H47) -> 495 | I48: =H48/B48 -> 0.11522346 | J48: =COUNTIF(Clean_Data!$G$2:$G$4314,">0")/B48 -> 0.5211825
A49: Note: Daily SD = SQRT((SUMIFS of squared returns - N x mean^2)/(N-1)), the sample standard deviation by year; annualised = daily SD x SQRT(365). 2026 = to 26 October.
A51: Table 5: Has volatility declined? Variance-ratio (F) test and volatility trend
A52: Measure | B52: Period 1 | C52: Period 2
A53: First year of period | B53: 2015 | C53: 2021
A54: Last year of period | B54: 2020 | C54: 2026
A55: Number of daily returns (N) | B55: =COUNTIFS(Clean_Data!$B$2:$B$4314,">="&B53,Clean_Data!$B$2:$B$4314,"<="&B54,Clean_Data!$G$2:$G$4314,">=-10") -> 2171 | C55: =COUNTIFS(Clean_Data!$B$2:$B$4314,">="&C53,Clean_Data!$B$2:$B$4314,"<="&C54,Clean_Data!$G$2:$G$4314,">=-10") -> 2125
A56: Mean daily log return | B56: =AVERAGEIFS(Clean_Data!$G$2:$G$4314,Clean_Data!$B$2:$B$4314,">="&B53,Clean_Data!$B$2:$B$4314,"<="&B54,Clean_Data!$G$2:$G$4314,">=-10") -> 0.0022407949 | C56: =AVERAGEIFS(Clean_Data!$G$2:$G$4314,Clean_Data!$B$2:$B$4314,">="&C53,Clean_Data!$B$2:$B$4314,"<="&C54,Clean_Data!$G$2:$G$4314,">=-10") -> 0.00047741476
A57: Variance of daily returns | B57: =(SUMIFS(Clean_Data!$H$2:$H$4314,Clean_Data!$B$2:$B$4314,">="&B53,Clean_Data!$B$2:$B$4314,"<="&B54,Clean_Data!$G$2:$G$4314,">=-10")-B55*B56^2)/(B55-1) -> 0.0015043758 | C57: =(SUMIFS(Clean_Data!$H$2:$H$4314,Clean_Data!$B$2:$B$4314,">="&C53,Clean_Data!$B$2:$B$4314,"<="&C54,Clean_Data!$G$2:$G$4314,">=-10")-C55*C56^2)/(C55-1) -> 0.00087681535
A58: Daily standard deviation | B58: =SQRT(B57) -> 0.038786284 | C58: =SQRT(C57) -> 0.029611068
A59: Annualised volatility | B59: =B58*SQRT(Clean_Data!$R$3) -> 0.74101092 | C59: =C58*SQRT(Clean_Data!$R$3) -> 0.56571866
A60: Change in annualised volatility (Period 2 vs Period 1) | B60: =C59-B59 -> -0.17529226 | C60: =C59/B59-1 -> -0.23655827 | D60: pp change | % change
A61: F statistic (larger variance / smaller variance) | B61: =MAX(B57,C57)/MIN(B57,C57) -> 1.7157271
A62: Degrees of freedom (numerator, denominator) | B62: =IF(B57>=C57,B55,C55)-1 -> 2170 | C62: =IF(B57>=C57,C55,B55)-1 -> 2124
A63: p-value (two-tailed) | B63: =MIN(1,2*_xlfn.F.DIST.RT(B61,B62,C62)) -> 2.0848299e-35
A64: Decision (5% level) | B64: =IF(B63<0.05,"Variances differ significantly","No significant difference") -> Variances differ significantly
A65: Trend in annual volatility, 2015-2025 (pp per year) | B65: =SLOPE(E36:E46,A36:A46) -> -0.021865356 | D65: SLOPE of Table 4 annualised volatility on year
A66: Correlation of annual volatility with year | B66: =CORREL(E36:E46,A36:A46) -> -0.41623847 | D66: CORREL (Pearson r)
A67: R-squared of volatility trend | B67: =RSQ(E36:E46,A36:A46) -> 0.17325446
A68: Annualised volatility, latest 365 days | B68: =_xlfn.STDEV.S(Clean_Data!G3950:G4314)*SQRT(Clean_Data!$R$3) -> 0.42061448 | D68: STDEV.S of last 365 daily returns x SQRT(365) | L68: Source: Table 6. The observed distribution is more peaked with fatter tails than the normal curve.
A69: Note: The F-test assumes normality; given the non-normality in Table 3 the p-value is indicative. Period-year inputs (blue) can be changed.
A71: Table 6: Frequency distribution of daily log returns vs the normal distribution
A72: Bin label (lower bound, %) | B72: Lower bound | C72: Upper bound | D72: Observed frequency | E72: Observed % | F72: Expected frequency (normal) | G72: Expected % (normal)
A73: =IF(B73<=-1,"<"&TEXT(C73*100,"0"),IF(C73>=1,">"&TEXT(B73*100,"0"),TEXT(B73*100,"0"))) -> <-15 | B73: -1 | C73: -0.15 | D73: =COUNTIFS(Clean_Data!$G$2:$G$4314,">="&B73,Clean_Data!$G$2:$G$4314,"<"&C73) -> 8 | E73: =D73/$B$8 -> 0.0018621974 | F73: =$B$8*(_xlfn.NORM.DIST(C73,$B$9,$B$11,TRUE())-_xlfn.NORM.DIST(B73,$B$9,$B$11,TRUE())) -> 0.02552022 | G73: =F73/$B$8 -> 5.9404609e-06
A74: =IF(B74<=-1,"<"&TEXT(C74*100,"0"),IF(C74>=1,">"&TEXT(B74*100,"0"),TEXT(B74*100,"0"))) -> -15 | B74: -0.15 | C74: -0.14 | D74: =COUNTIFS(Clean_Data!$G$2:$G$4314,">="&B74,Clean_Data!$G$2:$G$4314,"<"&C74) -> 6 | E74: =D74/$B$8 -> 0.001396648 | F74: =$B$8*(_xlfn.NORM.DIST(C74,$B$9,$B$11,TRUE())-_xlfn.NORM.DIST(B74,$B$9,$B$11,TRUE())) -> 0.066972149 | G74: =F74/$B$8 -> 1.558942e-05
A75: =IF(B75<=-1,"<"&TEXT(C75*100,"0"),IF(C75>=1,">"&TEXT(B75*100,"0"),TEXT(B75*100,"0"))) -> -14 | B75: -0.14 | C75: -0.13 | D75: =COUNTIFS(Clean_Data!$G$2:$G$4314,">="&B75,Clean_Data!$G$2:$G$4314,"<"&C75) -> 2 | E75: =D75/$B$8 -> 0.00046554935 | F75: =$B$8*(_xlfn.NORM.DIST(C75,$B$9,$B$11,TRUE())-_xlfn.NORM.DIST(B75,$B$9,$B$11,TRUE())) -> 0.21697165 | G75: =F75/$B$8 -> 5.0505505e-05
A76: =IF(B76<=-1,"<"&TEXT(C76*100,"0"),IF(C76>=1,">"&TEXT(B76*100,"0"),TEXT(B76*100,"0"))) -> -13 | B76: -0.13 | C76: -0.12 | D76: =COUNTIFS(Clean_Data!$G$2:$G$4314,">="&B76,Clean_Data!$G$2:$G$4314,"<"&C76) -> 7 | E76: =D76/$B$8 -> 0.0016294227 | F76: =$B$8*(_xlfn.NORM.DIST(C76,$B$9,$B$11,TRUE())-_xlfn.NORM.DIST(B76,$B$9,$B$11,TRUE())) -> 0.64682967 | G76: =F76/$B$8 -> 0.00015056557
A77: =IF(B77<=-1,"<"&TEXT(C77*100,"0"),IF(C77>=1,">"&TEXT(B77*100,"0"),TEXT(B77*100,"0"))) -> -12 | B77: -0.12 | C77: -0.11 | D77: =COUNTIFS(Clean_Data!$G$2:$G$4314,">="&B77,Clean_Data!$G$2:$G$4314,"<"&C77) -> 12 | E77: =D77/$B$8 -> 0.0027932961 | F77: =$B$8*(_xlfn.NORM.DIST(C77,$B$9,$B$11,TRUE())-_xlfn.NORM.DIST(B77,$B$9,$B$11,TRUE())) -> 1.774423 | G77: =F77/$B$8 -> 0.00041304074
A78: =IF(B78<=-1,"<"&TEXT(C78*100,"0"),IF(C78>=1,">"&TEXT(B78*100,"0"),TEXT(B78*100,"0"))) -> -11 | B78: -0.11 | C78: -0.1 | D78: =COUNTIFS(Clean_Data!$G$2:$G$4314,">="&B78,Clean_Data!$G$2:$G$4314,"<"&C78) -> 16 | E78: =D78/$B$8 -> 0.0037243948 | F78: =$B$8*(_xlfn.NORM.DIST(C78,$B$9,$B$11,TRUE())-_xlfn.NORM.DIST(B78,$B$9,$B$11,TRUE())) -> 4.4792641 | G78: =F78/$B$8 -> 0.0010426592
A79: =IF(B79<=-1,"<"&TEXT(C79*100,"0"),IF(C79>=1,">"&TEXT(B79*100,"0"),TEXT(B79*100,"0"))) -> -10 | B79: -0.1 | C79: -0.09 | D79: =COUNTIFS(Clean_Data!$G$2:$G$4314,">="&B79,Clean_Data!$G$2:$G$4314,"<"&C79) -> 11 | E79: =D79/$B$8 -> 0.0025605214 | F79: =$B$8*(_xlfn.NORM.DIST(C79,$B$9,$B$11,TRUE())-_xlfn.NORM.DIST(B79,$B$9,$B$11,TRUE())) -> 10.404957 | G79: =F79/$B$8 -> 0.0024220104
A80: =IF(B80<=-1,"<"&TEXT(C80*100,"0"),IF(C80>=1,">"&TEXT(B80*100,"0"),TEXT(B80*100,"0"))) -> -9 | B80: -0.09 | C80: -0.08 | D80: =COUNTIFS(Clean_Data!$G$2:$G$4314,">="&B80,Clean_Data!$G$2:$G$4314,"<"&C80) -> 18 | E80: =D80/$B$8 -> 0.0041899441 | F80: =$B$8*(_xlfn.NORM.DIST(C80,$B$9,$B$11,TRUE())-_xlfn.NORM.DIST(B80,$B$9,$B$11,TRUE())) -> 22.241274 | G80: =F80/$B$8 -> 0.0051772053
A81: =IF(B81<=-1,"<"&TEXT(C81*100,"0"),IF(C81>=1,">"&TEXT(B81*100,"0"),TEXT(B81*100,"0"))) -> -8 | B81: -0.08 | C81: -0.07 | D81: =COUNTIFS(Clean_Data!$G$2:$G$4314,">="&B81,Clean_Data!$G$2:$G$4314,"<"&C81) -> 32 | E81: =D81/$B$8 -> 0.0074487896 | F81: =$B$8*(_xlfn.NORM.DIST(C81,$B$9,$B$11,TRUE())-_xlfn.NORM.DIST(B81,$B$9,$B$11,TRUE())) -> 43.748824 | G81: =F81/$B$8 -> 0.010183618
A82: =IF(B82<=-1,"<"&TEXT(C82*100,"0"),IF(C82>=1,">"&TEXT(B82*100,"0"),TEXT(B82*100,"0"))) -> -7 | B82: -0.07 | C82: -0.06 | D82: =COUNTIFS(Clean_Data!$G$2:$G$4314,">="&B82,Clean_Data!$G$2:$G$4314,"<"&C82) -> 68 | E82: =D82/$B$8 -> 0.015828678 | F82: =$B$8*(_xlfn.NORM.DIST(C82,$B$9,$B$11,TRUE())-_xlfn.NORM.DIST(B82,$B$9,$B$11,TRUE())) -> 79.188446 | G82: =F82/$B$8 -> 0.018433065
A83: =IF(B83<=-1,"<"&TEXT(C83*100,"0"),IF(C83>=1,">"&TEXT(B83*100,"0"),TEXT(B83*100,"0"))) -> -6 | B83: -0.06 | C83: -0.05 | D83: =COUNTIFS(Clean_Data!$G$2:$G$4314,">="&B83,Clean_Data!$G$2:$G$4314,"<"&C83) -> 60 | E83: =D83/$B$8 -> 0.01396648 | F83: =$B$8*(_xlfn.NORM.DIST(C83,$B$9,$B$11,TRUE())-_xlfn.NORM.DIST(B83,$B$9,$B$11,TRUE())) -> 131.90073 | G83: =F83/$B$8 -> 0.030703149
A84: =IF(B84<=-1,"<"&TEXT(C84*100,"0"),IF(C84>=1,">"&TEXT(B84*100,"0"),TEXT(B84*100,"0"))) -> -5 | B84: -0.05 | C84: -0.04 | D84: =COUNTIFS(Clean_Data!$G$2:$G$4314,">="&B84,Clean_Data!$G$2:$G$4314,"<"&C84) -> 86 | E84: =D84/$B$8 -> 0.020018622 | F84: =$B$8*(_xlfn.NORM.DIST(C84,$B$9,$B$11,TRUE())-_xlfn.NORM.DIST(B84,$B$9,$B$11,TRUE())) -> 202.17319 | G84: =F84/$B$8 -> 0.047060798
... A104: =IF(B104<=-1,"<"&TEXT(C104*100,"0"),IF(C104>=1,">"&TEXT(B104*100,"0"),TEXT(B104*100,"0"))) -> >15 | B104: 0.15 | C104: 1 | D104: =COUNTIFS(Clean_Data!$G$2:$G$4314,">="&B104,Clean_Data!$G$2:$G$4314,"<"&C104) -> 7 | E104: =D104/$B$8 -> 0.0016294227 | F104: =$B$8*(_xlfn.NORM.DIST(C104,$B$9,$B$11,TRUE())-_xlfn.NORM.DIST(B104,$B$9,$B$11,TRUE())) -> 0.036593941 | G104: =F104/$B$8 -> 8.5181428e-06
A105: Total | D105: =SUM(D73:D104) -> 4296 | E105: =SUM(E73:E104) -> 1 | F105: =SUM(F73:F104) -> 4296 | G105: =SUM(G73:G104) -> 1
A106: Note: Bins are 1 percentage point wide (lower bound inclusive); outer bins (bounds +/-100%) capture all returns beyond +/-15%. Expected frequency = N x [NORM.DIST(upper) - NORM.DIST(lower)] using the Table 3 mean and SD.

Sheet Obj3_Risk
A1: Objective 3: Downside risk - Value at Risk, Expected Shortfall and drawdowns
A2: RO3: To quantify Bitcoin's downside risk using measures applied by financial institutions and assess the implications for treasury holdings, crypto payment acceptance and capital planning.
A4: Table 7: One-day Value at Risk (VaR) and Expected Shortfall (ES), daily simple returns
A5: Measure | B5: 95% confidence | C5: 99% confidence | D5: Method (Excel formula logic)
A6: Confidence level | B6: 0.95 | C6: 0.99 | D6: Input
A7: Tail probability | B7: =1-B6 -> 0.05 | C7: =1-C6 -> 0.01 | D7: 1 - confidence
A8: Number of daily returns (N) | B8: =COUNT(Clean_Data!$I$2:$I$4314) -> 4296 | C8: =COUNT(Clean_Data!$I$2:$I$4314) -> 4296 | D8: COUNT
A9: Mean daily return | B9: =AVERAGE(Clean_Data!$I$2:$I$4314) -> 0.0019641149 | C9: =AVERAGE(Clean_Data!$I$2:$I$4314) -> 0.0019641149 | D9: AVERAGE
A10: Standard deviation (daily) | B10: =_xlfn.STDEV.S(Clean_Data!$I$2:$I$4314) -> 0.034408716 | C10: =_xlfn.STDEV.S(Clean_Data!$I$2:$I$4314) -> 0.034408716 | D10: STDEV.S
A11: Historical VaR (loss) | B11: =-_xlfn.PERCENTILE.INC(Clean_Data!$I$2:$I$4314,B7) -> 0.052158646 | C11: =-_xlfn.PERCENTILE.INC(Clean_Data!$I$2:$I$4314,C7) -> 0.098257475 | D11: -PERCENTILE.INC(returns, tail)
A12: Parametric (normal) VaR (loss) | B12: =-(B9+_xlfn.NORM.S.INV(B7)*B10) -> 0.054633186 | C12: =-(C9+_xlfn.NORM.S.INV(C7)*C10) -> 0.078082528 | D12: -(mean + NORM.S.INV(tail) x SD)
A13: Historical Expected Shortfall (loss) | B13: =-AVERAGEIF(Clean_Data!$I$2:$I$4314,"<="&-B11) -> 0.079715268 | C13: =-AVERAGEIF(Clean_Data!$I$2:$I$4314,"<="&-C11) -> 0.12649979 | D13: -AVERAGEIF(returns <= -VaR)
A14: Parametric (normal) Expected Shortfall | B14: =-(B9-B10*_xlfn.NORM.S.DIST(_xlfn.NORM.S.INV(B7),FALSE())/B7) -> 0.069011184 | C14: =-(C9-C10*_xlfn.NORM.S.DIST(_xlfn.NORM.S.INV(C7),FALSE())/C7) -> 0.089742484 | D14: -(mean - SD x pdf(z)/tail)
A15: Historical / normal VaR ratio | B15: =B11/B12 -> 0.95470629 | C15: =C11/C12 -> 1.2583798 | D15: Model under/over-statement
A16: Backtest: days with loss > normal VaR | B16: =COUNTIF(Clean_Data!$I$2:$I$4314,"<"&-B12) -> 201 | C16: =COUNTIF(Clean_Data!$I$2:$I$4314,"<"&-C12) -> 79 | D16: COUNTIF(returns < -normal VaR)
A17: Backtest: expected exceedances | B17: =B8*B7 -> 214.8 | C17: =C8*C7 -> 42.96 | D17: N x tail probability
A18: Exceedance ratio (actual / expected) | B18: =B16/B17 -> 0.93575419 | C18: =C16/C17 -> 1.8389199 | D18: >1 = normal model understates risk
A19: Note: VaR and ES are reported as positive loss percentages of position value over one day. Simple return = Pt / Pt-1 - 1 (consecutive days from 20-Jan-2015).
A21: Table 8: Illustrative loss exposure for a US$1 million Bitcoin position
A22: Measure | B22: 95% confidence | C22: 99% confidence | D22: Method (Excel formula logic)
A23: Position value (US$) | B23: 1000000 | D23: Input (e.g. corporate treasury or bank exposure)
A24: Holding period for regulatory-style VaR (days) | B24: 10 | D24: Input (Basel market-risk convention) | M24: Source: Clean_Data column L (price / running peak - 1).
A25: 1-day historical VaR (US$) | B25: =$B$23*B11 -> 52158.646 | C25: =$B$23*C11 -> 98257.475 | D25: Position x historical VaR
A26: 1-day historical Expected Shortfall (US$) | B26: =$B$23*B13 -> 79715.268 | C26: =$B$23*C13 -> 126499.79 | D26: Position x historical ES
A27: 10-day VaR, square-root-of-time (US$) | B27: =B25*SQRT($B$24) -> 164940.12 | C27: =C25*SQRT($B$24) -> 310717.42 | D27: 1-day VaR x SQRT(10)
A28: Basel risk weight, Group 2 cryptoassets | B28: 12.5 | D28: Input: BCBS (2022) - 1250% risk weight
A29: Minimum total capital ratio | B29: 0.08 | D29: Input: Basel III minimum (8%)
A30: Capital required under Basel treatment (US$) | B30: =B23*B28*B29 -> 1000000 | D30: Position x risk weight x 8%
A31: Capital / 10-day 99% VaR (x) | B31: =B30/C27 -> 3.2183584 | D31: Prudential buffer relative to statistical VaR
A32: Note: Blue cells are inputs. Square-root-of-time scaling assumes independent returns and understates risk when tails are fat (see Table 7).
A34: Table 9: Probability of loss by holding horizon (settlement / treasury risk)
A35: Holding horizon | B35: N (windows) | C35: P(any loss) | D35: P(loss > 5%) | E35: P(loss > 10%) | F35: P(loss > 20%) | G35: 5th percentile return | H35: Worst return | I35: Best return
A36: Loss threshold (input) | D36: 0.05 | E36: 0.1 | F36: 0.2
A37: 1 day | B37: =COUNT(Clean_Data!$I$2:$I$4314) -> 4296 | C37: =COUNTIF(Clean_Data!$I$2:$I$4314,"<0")/B37 -> 0.4788175 | D37: =COUNTIF(Clean_Data!$I$2:$I$4314,"<"&-D$36)/$B37 -> 0.053538175 | E37: =COUNTIF(Clean_Data!$I$2:$I$4314,"<"&-E$36)/$B37 -> 0.0097765363 | F37: =COUNTIF(Clean_Data!$I$2:$I$4314,"<"&-F$36)/$B37 -> 0.00023277467 | G37: =_xlfn.PERCENTILE.INC(Clean_Data!$I$2:$I$4314,0.05) -> -0.052158646 | H37: =MIN(Clean_Data!$I$2:$I$4314) -> -0.37413755 | I37: =MAX(Clean_Data!$I$2:$I$4314) -> 0.2720198
A38: 7 days | B38: =COUNT(Clean_Data!$N$2:$N$4314) -> 4290 | C38: =COUNTIF(Clean_Data!$N$2:$N$4314,"<0")/B38 -> 0.45431235 | D38: =COUNTIF(Clean_Data!$N$2:$N$4314,"<"&-D$36)/$B38 -> 0.18811189 | E38: =COUNTIF(Clean_Data!$N$2:$N$4314,"<"&-E$36)/$B38 -> 0.082983683 | F38: =COUNTIF(Clean_Data!$N$2:$N$4314,"<"&-F$36)/$B38 -> 0.014219114 | G38: =_xlfn.PERCENTILE.INC(Clean_Data!$N$2:$N$4314,0.05) -> -0.1281142 | H38: =MIN(Clean_Data!$N$2:$N$4314) -> -0.44994013 | I38: =MAX(Clean_Data!$N$2:$N$4314) -> 0.75603453
A39: 30 days | B39: =COUNT(Clean_Data!$O$2:$O$4314) -> 4267 | C39: =COUNTIF(Clean_Data!$O$2:$O$4314,"<0")/B39 -> 0.41996719 | D39: =COUNTIF(Clean_Data!$O$2:$O$4314,"<"&-D$36)/$B39 -> 0.29153972 | E39: =COUNTIF(Clean_Data!$O$2:$O$4314,"<"&-E$36)/$B39 -> 0.20482775 | F39: =COUNTIF(Clean_Data!$O$2:$O$4314,"<"&-F$36)/$B39 -> 0.076165925 | G39: =_xlfn.PERCENTILE.INC(Clean_Data!$O$2:$O$4314,0.05) -> -0.23559075 | H39: =MIN(Clean_Data!$O$2:$O$4314) -> -0.59616387 | I39: =MAX(Clean_Data!$O$2:$O$4314) -> 2.0120737
A40: Note: 7- and 30-day returns use overlapping daily windows (Clean_Data columns N and O). Relevant to businesses holding crypto receipts before conversion to fiat.
A42: Table 10: Maximum drawdown and major drawdown episodes
A43: Episode | B43: Window start | C43: Window end | D43: Peak date | E43: Peak price (US$) | F43: Trough date | G43: Trough price (US$) | H43: Drawdown | I43: Days peak to trough | J43: Recovery date (new high) | K43: Days trough to recovery
A44: 2017-18: post-ICO boom correction | B44: 42887 | C44: 43555 | D44: =_xlfn.MINIFS(Clean_Data!$A$2:$A$4314,Clean_Data!$C$2:$C$4314,E44,Clean_Data!$A$2:$A$4314,">="&B44,Clean_Data!$A$2:$A$4314,"<="&C44) -> 43085 | E44: =_xlfn.MAXIFS(Clean_Data!$C$2:$C$4314,Clean_Data!$A$2:$A$4314,">="&B44,Clean_Data!$A$2:$A$4314,"<="&C44) -> 19650.01 | F44: =_xlfn.MINIFS(Clean_Data!$A$2:$A$4314,Clean_Data!$C$2:$C$4314,G44,Clean_Data!$A$2:$A$4314,">="&D44,Clean_Data!$A$2:$A$4314,"<="&C44) -> 43449 | G44: =_xlfn.MINIFS(Clean_Data!$C$2:$C$4314,Clean_Data!$A$2:$A$4314,">="&D44,Clean_Data!$A$2:$A$4314,"<="&C44) -> 3183 | H44: =G44/E44-1 -> -0.83801535 | I44: =F44-D44 -> 364 | J44: =IF(_xlfn.MINIFS(Clean_Data!$A$2:$A$4314,Clean_Data!$A$2:$A$4314,">"&F44,Clean_Data!$C$2:$C$4314,">="&E44)=0,"Not yet recovered",_xlfn.MINIFS(Clean_Data!$A$2:$A$4314,Clean_Data!$A$2:$A$4314,">"&F44,Clean_Data!$C$2:$C$4314,">="&E44)) -> 44165 | K44: =IF(ISNUMBER(J44),J44-F44,"n/a") -> 716
A45: 2019-20: incl. COVID-19 crash (Mar 2020) | B45: 43617 | C45: 43951 | D45: =_xlfn.MINIFS(Clean_Data!$A$2:$A$4314,Clean_Data!$C$2:$C$4314,E45,Clean_Data!$A$2:$A$4314,">="&B45,Clean_Data!$A$2:$A$4314,"<="&C45) -> 43642 | E45: =_xlfn.MAXIFS(Clean_Data!$C$2:$C$4314,Clean_Data!$A$2:$A$4314,">="&B45,Clean_Data!$A$2:$A$4314,"<="&C45) -> 12902.52 | F45: =_xlfn.MINIFS(Clean_Data!$A$2:$A$4314,Clean_Data!$C$2:$C$4314,G45,Clean_Data!$A$2:$A$4314,">="&D45,Clean_Data!$A$2:$A$4314,"<="&C45) -> 43902 | G45: =_xlfn.MINIFS(Clean_Data!$C$2:$C$4314,Clean_Data!$A$2:$A$4314,">="&D45,Clean_Data!$A$2:$A$4314,"<="&C45) -> 4980 | H45: =G45/E45-1 -> -0.61402889 | I45: =F45-D45 -> 260 | J45: =IF(_xlfn.MINIFS(Clean_Data!$A$2:$A$4314,Clean_Data!$A$2:$A$4314,">"&F45,Clean_Data!$C$2:$C$4314,">="&E45)=0,"Not yet recovered",_xlfn.MINIFS(Clean_Data!$A$2:$A$4314,Clean_Data!$A$2:$A$4314,">"&F45,Clean_Data!$C$2:$C$4314,">="&E45)) -> 44126 | K45: =IF(ISNUMBER(J45),J45-F45,"n/a") -> 224
A46: 2021-22: Terra-Luna and FTX failures | B46: 44197 | C46: 44926 | D46: =_xlfn.MINIFS(Clean_Data!$A$2:$A$4314,Clean_Data!$C$2:$C$4314,E46,Clean_Data!$A$2:$A$4314,">="&B46,Clean_Data!$A$2:$A$4314,"<="&C46) -> 44508 | E46: =_xlfn.MAXIFS(Clean_Data!$C$2:$C$4314,Clean_Data!$A$2:$A$4314,">="&B46,Clean_Data!$A$2:$A$4314,"<="&C46) -> 67510.06 | F46: =_xlfn.MINIFS(Clean_Data!$A$2:$A$4314,Clean_Data!$C$2:$C$4314,G46,Clean_Data!$A$2:$A$4314,">="&D46,Clean_Data!$A$2:$A$4314,"<="&C46) -> 44886 | G46: =_xlfn.MINIFS(Clean_Data!$C$2:$C$4314,Clean_Data!$A$2:$A$4314,">="&D46,Clean_Data!$A$2:$A$4314,"<="&C46) -> 15755.75 | H46: =G46/E46-1 -> -0.76661626 | I46: =F46-D46 -> 378 | J46: =IF(_xlfn.MINIFS(Clean_Data!$A$2:$A$4314,Clean_Data!$A$2:$A$4314,">"&F46,Clean_Data!$C$2:$C$4314,">="&E46)=0,"Not yet recovered",_xlfn.MINIFS(Clean_Data!$A$2:$A$4314,Clean_Data!$A$2:$A$4314,">"&F46,Clean_Data!$C$2:$C$4314,">="&E46)) -> 45355 | K46: =IF(ISNUMBER(J46),J46-F46,"n/a") -> 469 | M46: Source: Table 7. Historical tail losses exceed normal-model estimates at 99% confidence.
A47: 2025-26: correction from Oct 2025 high | B47: 45658 | C47: =MAX(Clean_Data!$A$2:$A$4314) -> 46321 | D47: =_xlfn.MINIFS(Clean_Data!$A$2:$A$4314,Clean_Data!$C$2:$C$4314,E47,Clean_Data!$A$2:$A$4314,">="&B47,Clean_Data!$A$2:$A$4314,"<="&C47) -> 45935 | E47: =_xlfn.MAXIFS(Clean_Data!$C$2:$C$4314,Clean_Data!$A$2:$A$4314,">="&B47,Clean_Data!$A$2:$A$4314,"<="&C47) -> 124720.09 | F47: =_xlfn.MINIFS(Clean_Data!$A$2:$A$4314,Clean_Data!$C$2:$C$4314,G47,Clean_Data!$A$2:$A$4314,">="&D47,Clean_Data!$A$2:$A$4314,"<="&C47) -> 46203 | G47: =_xlfn.MINIFS(Clean_Data!$C$2:$C$4314,Clean_Data!$A$2:$A$4314,">="&D47,Clean_Data!$A$2:$A$4314,"<="&C47) -> 58585.96 | H47: =G47/E47-1 -> -0.53026044 | I47: =F47-D47 -> 268 | J47: =IF(_xlfn.MINIFS(Clean_Data!$A$2:$A$4314,Clean_Data!$A$2:$A$4314,">"&F47,Clean_Data!$C$2:$C$4314,">="&E47)=0,"Not yet recovered",_xlfn.MINIFS(Clean_Data!$A$2:$A$4314,Clean_Data!$A$2:$A$4314,">"&F47,Clean_Data!$C$2:$C$4314,">="&E47)) -> Not yet recovered | K47: =IF(ISNUMBER(J47),J47-F47,"n/a") -> n/a
A48: Full-sample maximum drawdown | F48: =INDEX(Clean_Data!$A$2:$A$4314,MATCH(H48,Clean_Data!$L$2:$L$4314,0)) -> 43449 | G48: =INDEX(Clean_Data!$C$2:$C$4314,MATCH(H48,Clean_Data!$L$2:$L$4314,0)) -> 3183 | H48: =MIN(Clean_Data!$L$2:$L$4314) -> -0.83801535
A49: Current drawdown from all-time high | H49: =INDEX(Clean_Data!$L$2:$L$4314,MATCH(MAX(Clean_Data!$A$2:$A$4314),Clean_Data!$A$2:$A$4314,0)) -> -0.35811119
A50: Share of days more than 50% below running peak | H50: =COUNTIF(Clean_Data!$L$2:$L$4314,"<-0.5")/COUNT(Clean_Data!$L$2:$L$4314) -> 0.31231162
A51: Note: Peak = MAXIFS within window; trough = MINIFS after the peak; recovery = first later date with price >= peak. Window dates (blue) are analyst inputs.
A53: Table 11: Risk-adjusted performance by year, 2015-2026
A54: Year | B54: Annual return | C54: Annualised volatility | D54: Return / volatility ratio | E54: Deepest drawdown from all-time high | F54: Days with loss > 5% | G54: Days with gain > 5%
A55: 2015 | B55: =Obj1_Value!I29 -> 0.26573529 | C55: =Obj2_Volatility!E36 -> 0.5717719 | D55: =B55/C55 -> 0.46475753 | E55: =_xlfn.MINIFS(Clean_Data!$L$2:$L$4314,Clean_Data!$B$2:$B$4314,A55) -> -0.68253968 | F55: =COUNTIFS(Clean_Data!$B$2:$B$4314,A55,Clean_Data!$I$2:$I$4314,"<-0.05") -> 12 | G55: =COUNTIFS(Clean_Data!$B$2:$B$4314,A55,Clean_Data!$I$2:$I$4314,">0.05") -> 18
A56: 2016 | B56: =Obj1_Value!I30 -> 1.2618102 | C56: =Obj2_Volatility!E37 -> 0.4987813 | D56: =B56/C56 -> 2.5297864 | E56: =_xlfn.MINIFS(Clean_Data!$L$2:$L$4314,Clean_Data!$B$2:$B$4314,A56) -> -0.30176938 | F56: =COUNTIFS(Clean_Data!$B$2:$B$4314,A56,Clean_Data!$I$2:$I$4314,"<-0.05") -> 11 | G56: =COUNTIFS(Clean_Data!$B$2:$B$4314,A56,Clean_Data!$I$2:$I$4314,">0.05") -> 14
A57: 2017 | B57: =Obj1_Value!I31 -> 13.242405 | C57: =Obj2_Volatility!E38 -> 0.93144058 | D57: =B57/C57 -> 14.217123 | E57: =_xlfn.MINIFS(Clean_Data!$L$2:$L$4314,Clean_Data!$B$2:$B$4314,A57) -> -0.36252326 | F57: =COUNTIFS(Clean_Data!$B$2:$B$4314,A57,Clean_Data!$I$2:$I$4314,"<-0.05") -> 39 | G57: =COUNTIFS(Clean_Data!$B$2:$B$4314,A57,Clean_Data!$I$2:$I$4314,">0.05") -> 53
A58: 2018 | B58: =Obj1_Value!I32 -> -0.73369217 | C58: =Obj2_Volatility!E39 -> 0.83717888 | D58: =B58/C58 -> -0.87638639 | E58: =_xlfn.MINIFS(Clean_Data!$L$2:$L$4314,Clean_Data!$B$2:$B$4314,A58) -> -0.83801535 | F58: =COUNTIFS(Clean_Data!$B$2:$B$4314,A58,Clean_Data!$I$2:$I$4314,"<-0.05") -> 45 | G58: =COUNTIFS(Clean_Data!$B$2:$B$4314,A58,Clean_Data!$I$2:$I$4314,">0.05") -> 29
A59: 2019 | B59: =Obj1_Value!I33 -> 0.9388628 | C59: =Obj2_Volatility!E40 -> 0.70436589 | D59: =B59/C59 -> 1.3329192 | E59: =_xlfn.MINIFS(Clean_Data!$L$2:$L$4314,Clean_Data!$B$2:$B$4314,A59) -> -0.82905861 | F59: =COUNTIFS(Clean_Data!$B$2:$B$4314,A59,Clean_Data!$I$2:$I$4314,"<-0.05") -> 19 | G59: =COUNTIFS(Clean_Data!$B$2:$B$4314,A59,Clean_Data!$I$2:$I$4314,">0.05") -> 29
A60: 2020 | B60: =Obj1_Value!I34 -> 3.0551732 | C60: =Obj2_Volatility!E41 -> 0.79267148 | D60: =B60/C60 -> 3.8542741 | E60: =_xlfn.MINIFS(Clean_Data!$L$2:$L$4314,Clean_Data!$B$2:$B$4314,A60) -> -0.74656501 | F60: =COUNTIFS(Clean_Data!$B$2:$B$4314,A60,Clean_Data!$I$2:$I$4314,"<-0.05") -> 17 | G60: =COUNTIFS(Clean_Data!$B$2:$B$4314,A60,Clean_Data!$I$2:$I$4314,">0.05") -> 29
A61: 2021 | B61: =Obj1_Value!I35 -> 0.59316077 | C61: =Obj2_Volatility!E42 -> 0.80549875 | D61: =B61/C61 -> 0.73638944 | E61: =_xlfn.MINIFS(Clean_Data!$L$2:$L$4314,Clean_Data!$B$2:$B$4314,A61) -> -0.53207398 | F61: =COUNTIFS(Clean_Data!$B$2:$B$4314,A61,Clean_Data!$I$2:$I$4314,"<-0.05") -> 36 | G61: =COUNTIFS(Clean_Data!$B$2:$B$4314,A61,Clean_Data!$I$2:$I$4314,">0.05") -> 40
A62: 2022 | B62: =Obj1_Value!I36 -> -0.64253147 | C62: =Obj2_Volatility!E43 -> 0.64465865 | D62: =B62/C62 -> -0.99670029 | E62: =_xlfn.MINIFS(Clean_Data!$L$2:$L$4314,Clean_Data!$B$2:$B$4314,A62) -> -0.76661626 | F62: =COUNTIFS(Clean_Data!$B$2:$B$4314,A62,Clean_Data!$I$2:$I$4314,"<-0.05") -> 23 | G62: =COUNTIFS(Clean_Data!$B$2:$B$4314,A62,Clean_Data!$I$2:$I$4314,">0.05") -> 14
A63: 2023 | B63: =Obj1_Value!I37 -> 1.5588761 | C63: =Obj2_Volatility!E44 -> 0.43791878 | D63: =B63/C63 -> 3.5597379 | E63: =_xlfn.MINIFS(Clean_Data!$L$2:$L$4314,Clean_Data!$B$2:$B$4314,A63) -> -0.75388587 | F63: =COUNTIFS(Clean_Data!$B$2:$B$4314,A63,Clean_Data!$I$2:$I$4314,"<-0.05") -> 7 | G63: =COUNTIFS(Clean_Data!$B$2:$B$4314,A63,Clean_Data!$I$2:$I$4314,">0.05") -> 16
A64: 2024 | B64: =Obj1_Value!I38 -> 1.2312494 | C64: =Obj2_Volatility!E45 -> 0.52954445 | D64: =B64/C64 -> 2.3251106 | E64: =_xlfn.MINIFS(Clean_Data!$L$2:$L$4314,Clean_Data!$B$2:$B$4314,A64) -> -0.41419634 | F64: =COUNTIFS(Clean_Data!$B$2:$B$4314,A64,Clean_Data!$I$2:$I$4314,"<-0.05") -> 11 | G64: =COUNTIFS(Clean_Data!$B$2:$B$4314,A64,Clean_Data!$I$2:$I$4314,">0.05") -> 16
A65: 2025 | B65: =Obj1_Value!I39 -> -0.070855432 | C65: =Obj2_Volatility!E46 -> 0.41901813 | D65: =B65/C65 -> -0.16909872 | E65: =_xlfn.MINIFS(Clean_Data!$L$2:$L$4314,Clean_Data!$B$2:$B$4314,A65) -> -0.319869 | F65: =COUNTIFS(Clean_Data!$B$2:$B$4314,A65,Clean_Data!$I$2:$I$4314,"<-0.05") -> 6 | G65: =COUNTIFS(Clean_Data!$B$2:$B$4314,A65,Clean_Data!$I$2:$I$4314,">0.05") -> 7
A66: 2026 | B66: =Obj1_Value!I40 -> -0.087114236 | C66: =Obj2_Volatility!E47 -> 0.42413404 | D66: =B66/C66 -> -0.20539317 | E66: =_xlfn.MINIFS(Clean_Data!$L$2:$L$4314,Clean_Data!$B$2:$B$4314,A66) -> -0.53026044 | F66: =COUNTIFS(Clean_Data!$B$2:$B$4314,A66,Clean_Data!$I$2:$I$4314,"<-0.05") -> 4 | G66: =COUNTIFS(Clean_Data!$B$2:$B$4314,A66,Clean_Data!$I$2:$I$4314,">0.05") -> 9
A67: Average 2015-2025 | B67: =AVERAGE(B55:B65) -> 1.8818358 | C67: =AVERAGE(C55:C65) -> 0.65207716 | D67: =AVERAGE(D55:D65) -> 2.4525375 | F67: =SUM(F55:F66) -> 230 | G67: =SUM(G55:G66) -> 274
A68: Note: Green cells link to Obj1_Value and Obj2_Volatility. Ratio uses a zero risk-free rate. F and G totals cover 2015-2026. 2026 = year to date. | M68: Source: Table 9.
M90: Source: Table 11. Each point is one full calendar year.

Sheet Summary
A1: Summary of key empirical findings
A2: All values link to the objective worksheets (green = cross-sheet link).
A4: Table 12: Key findings by research objective
A5: Research objective | B5: Key metric | C5: Value | D5: Analytical reading
A6: RO1 Value | B6: Price multiple, Dec 2014 - Oct 2026 | C6: =Obj1_Value!B12 -> 216.36873 | D6: Exceptional long-run value creation for early holders
A7: RO1 Value | B7: Compound annual growth rate (CAGR) | C7: =Obj1_Value!B13 -> 0.57112642 | D7: Growth far above traditional asset classes over the period
A8: RO1 Value | B8: Implied annual trend growth (log-linear) | C8: =Obj1_Value!B22 -> 0.66225567 | D8: Strong upward trend, but growth rate is uneven across cycles
A9: RO1 Value | B9: R-squared of log-linear trend | C9: =Obj1_Value!B23 -> 0.86167591 | D9: Trend explains most of the variation in log price
A10: RO1 Value | B10: Negative calendar years (2015-2025) | C10: =Obj1_Value!B48 -> 3 | D10: Value gains are interrupted by deep bear markets
A11: RO1 Value | B11: Latest price vs all-time high | C11: =Obj1_Value!B20 -> -0.35811119 | D11: Market currently trades below its 2025 peak
A12: RO2 Volatility | B12: Annualised volatility, full sample | C12: =Obj2_Volatility!B15 -> 0.66028526 | D12: Very high relative to traditional financial assets
A13: RO2 Volatility | B13: Excess kurtosis of daily returns | C13: =Obj2_Volatility!B18 -> 11.958703 | D13: Fat tails: extreme moves far more frequent than normal
A14: RO2 Volatility | B14: Jarque-Bera p-value | C14: =Obj2_Volatility!B21 -> 0 | D14: Normality rejected - normal-based models are unreliable
A15: RO2 Volatility | B15: Fat-tail ratio, |daily move| > 10% | C15: =Obj2_Volatility!B31 -> 5.6404701 | D15: Very large moves occur far more often than a normal model predicts
A16: RO2 Volatility | B16: Annualised volatility, Period 1 (2015-2020) | C16: =Obj2_Volatility!B59 -> 0.74101092 | D16: Earlier, less mature market
A17: RO2 Volatility | B17: Annualised volatility, Period 2 (2021-2026) | C17: =Obj2_Volatility!C59 -> 0.56571866 | D17: Lower volatility in the institutional era
A18: RO2 Volatility | B18: F-test p-value (Period 1 vs 2) | C18: =Obj2_Volatility!B63 -> 2.0848299e-35 | D18: Tests whether the decline is statistically significant
A19: RO2 Volatility | B19: Annualised volatility, latest 365 days | C19: =Obj2_Volatility!B68 -> 0.42061448 | D19: Current volatility regime
A20: RO3 Risk | B20: 1-day historical VaR (99%) | C20: =Obj3_Risk!C11 -> 0.098257475 | D20: Loss exceeded on about 1 day in 100
A21: RO3 Risk | B21: 1-day historical Expected Shortfall (99%) | C21: =Obj3_Risk!C13 -> 0.12649979 | D21: Average loss on the worst 1% of days
A22: RO3 Risk | B22: Normal-VaR exceedance ratio (99%) | C22: =Obj3_Risk!C18 -> 1.8389199 | D22: Normal model understates tail risk
A23: RO3 Risk | B23: 10-day 99% VaR on US$1m position | C23: =Obj3_Risk!C27 -> 310717.42 | D23: Regulatory-horizon loss estimate
A24: RO3 Risk | B24: Probability of >10% loss over 30 days | C24: =Obj3_Risk!E39 -> 0.20482775 | D24: Settlement / treasury risk for businesses
A25: RO3 Risk | B25: Full-sample maximum drawdown | C25: =Obj3_Risk!H48 -> -0.83801535 | D25: Worst peak-to-trough loss in the sample
A26: RO3 Risk | B26: Current drawdown from all-time high | C26: =Obj3_Risk!H49 -> -0.35811119 | D26: Unrealised loss for buyers at the 2025 peak
A27: Source: Author's calculations using FRED (2026) series CBBTCUSD.

Sheet Checks
A1: Formula integrity checks
A2: Independent formula routes should give identical results; status shows OK when |difference| < 0.000001.
A4: Check | B4: Route 1 | C4: Route 2 | D4: Difference | E4: Status
A5: Raw observations = clean observations | B5: =COUNT(Raw_Data!B:B) -> 4313 | C5: =COUNT(Clean_Data!$C$2:$C$4314) -> 4313 | D5: =B5-C5 -> 0 | E5: =IF(ABS(D5)<0.000001,"OK","CHECK") -> OK
A6: Sum of annual observations = total observations | B6: =Obj1_Value!B41 -> 4313 | C6: =COUNT(Clean_Data!$C$2:$C$4314) -> 4313 | D6: =B6-C6 -> 0 | E6: =IF(ABS(D6)<0.000001,"OK","CHECK") -> OK
A7: Cumulative log return: SUM of returns = LN(latest/opening) | B7: =Obj1_Value!B14 -> 5.376984 | C7: =LN(Obj1_Value!B9/Obj1_Value!B7) -> 5.376984 | D7: =B7-C7 -> 0 | E7: =IF(ABS(D7)<0.000001,"OK","CHECK") -> OK
A8: Sum of annual log returns = cumulative log return | B8: =Obj1_Value!J41 -> 5.376984 | C8: =Obj1_Value!B14 -> 5.376984 | D8: =B8-C8 -> 0 | E8: =IF(ABS(D8)<0.000001,"OK","CHECK") -> OK
A9: Max of annual maxima = all-time high | B9: =Obj1_Value!G41 -> 124720.09 | C9: =Obj1_Value!B16 -> 124720.09 | D9: =B9-C9 -> 0 | E9: =IF(ABS(D9)<0.000001,"OK","CHECK") -> OK
A10: Full-sample SD: SUMIFS route = STDEV.S | B10: =Obj2_Volatility!D48 -> 0.03456091 | C10: =Obj2_Volatility!B11 -> 0.03456091 | D10: =B10-C10 -> 0 | E10: =IF(ABS(D10)<0.000001,"OK","CHECK") -> OK
A11: Annual N in Table 4 sums to N in Table 3 | B11: =Obj2_Volatility!B48 -> 4296 | C11: =Obj2_Volatility!B8 -> 4296 | D11: =B11-C11 -> 0 | E11: =IF(ABS(D11)<0.000001,"OK","CHECK") -> OK
A12: Histogram frequencies sum to N | B12: =Obj2_Volatility!D105 -> 4296 | C12: =Obj2_Volatility!B8 -> 4296 | D12: =B12-C12 -> 0 | E12: =IF(ABS(D12)<0.000001,"OK","CHECK") -> OK
A13: Analysis-sample returns = consecutive days from start date | B13: =Obj2_Volatility!B8 -> 4296 | C13: =COUNTIFS(Clean_Data!$D$2:$D$4314,1,Clean_Data!$A$2:$A$4314,">="&Clean_Data!R2) -> 4296 | D13: =B13-C13 -> 0 | E13: =IF(ABS(D13)<0.000001,"OK","CHECK") -> OK
A14: Simple-return count = log-return count | B14: =Obj3_Risk!B8 -> 4296 | C14: =Obj2_Volatility!B8 -> 4296 | D14: =B14-C14 -> 0 | E14: =IF(ABS(D14)<0.000001,"OK","CHECK") -> OK
A16: All checks passed | B16: =IF(COUNTIF(E5:E14,"OK")=10,"YES","NO") -> YES
